{"ocr_results":[{"text":"《山花》今年国庆节要出片","box":[[357,149],[957,133],[958,187],[359,203]]},{"text":"些差异的，因为是意点影片，","box":[[1951,202],[2560,198],[2560,243],[1952,247]]},{"text":"三部车命历史趣材，77年八一要宪成","box":[[347,255],[1199,238],[1200,291],[348,307]]},{"text":"要搞出个落实的计划，提出一些切实可行自有力措族，完成任","box":[[2050,300],[3378,307],[3378,361],[2049,353]]},{"text":"今天，已经把重点片任务提上来了，省委和厂党变要报据这个","box":[[332,345],[1699,333],[1699,406],[332,418]]},{"text":"务的退路已经培死，这就要保证洗入生活的时间，要抓得紧，了解","box":[[1946,404],[3382,409],[3382,467],[1946,463]]},{"text":"情况，统算安排一下，","box":[[239,471],[697,471],[697,516],[239,516]]},{"text":"得深。","box":[[1943,513],[2067,517],[2066,577],[1941,573]]},{"text":"三个年命历史题材完成的退路要境死，77年8月1日一定要","box":[[329,566],[1693,560],[1693,627],[329,633]]},{"text":"《长征》组之可以向成荫同志谈谈，他拍过《万水千山》","box":[[2057,620],[3309,624],[3309,682],[2057,678]]},{"text":"奋斗出来","box":[[216,685],[447,685],[447,742],[216,742]]},{"text":"上海南爱已经在作准备工作，为创作在准备材料","box":[[2044,730],[3117,729],[3117,784],[2044,786]]},{"text":"关于长征题材，是写金过程还是写一段，于会泳已经讲了：写","box":[[332,786],[1706,789],[1706,857],[332,854]]},{"text":"要是没有措旅，任务就容易落空，","box":[[2052,842],[2767,836],[2768,889],[2053,895]]},{"text":"会过程或写一个部分都可以，如写一个局部，也要写出长征的意义","box":[[209,899],[1692,906],[1692,966],[209,959]]},{"text":"大家对文化部申影局要做些什么准备，如开介绍信去军委联系，","box":[[2047,949],[3424,943],[3424,996],[2047,1002]]},{"text":"和全貌，如写全过程，可以把四渡赤水带出，因这一段专题反映了，","box":[[207,1008],[1709,1021],[1709,1084],[206,1071]]},{"text":"有版片、军事预算等等，各创作组和厂可以提出来，要支持创作","box":[[1949,1053],[3401,1049],[3401,1103],[1949,1107]]},{"text":"关于《井岗山》，领导没有具体规定写那一段。刚才树元说的，","box":[[302,1124],[1709,1138],[1709,1196],[301,1183]]},{"text":"组和厂，力争按期完成任务。","box":[[1947,1162],[2572,1161],[2572,1216],[1947,1218]]},{"text":"是井冈山斗争的重要的一段，但还有没有别的方案？可以向上海市","box":[[192,1241],[1683,1250],[1683,1302],[192,1293]]},{"text":"四个大厂都有人在，把有关的几个事再说说","box":[[2054,1276],[3029,1273],[3029,1322],[2054,1325]]},{"text":"委汇报，请上海市委定，中央领导没有具体规定，王树元成荫、","box":[[191,1350],[1649,1366],[1648,1420],[190,1404]]},{"text":"一七六年的仓作生产计划，上次电影会议已经谈了，但今年","box":[[2058,1385],[3412,1385],[3412,1433],[2058,1433]]},{"text":"刘是同志，要立即向上浴市委汇报，有靠大间题可向中央请示，力","box":[[186,1463],[1683,1481],[1683,1535],[186,1517]]},{"text":"颂文化大車命的故喜片一部也没有，这是今年的宣传的鱼点内容，","box":[[1953,1494],[3444,1493],[3444,1542],[1953,1543]]},{"text":"争廿号之前拿出一个落实的计划，今天是九号，明天是十号，用十","box":[[184,1577],[1688,1598],[1687,1653],[183,1632]]},{"text":"是要回击石倾翻案风，可是没有故事片，希望四个厂慈想怎么办？","box":[[1950,1603],[3404,1605],[3404,1654],[1950,1653]]},{"text":"天拿出一个计划，还要增加哪些创作人员，中央领导的指示精神可","box":[[192,1692],[1699,1711],[1699,1771],[192,1751]]},{"text":"希望写出揭露不肯改悔的走资派，与此柜对立的是坚持毛","box":[[2060,1715],[3425,1715],[3425,1765],[2060,1765]]},{"text":"以加些青年，我已和上海市委联系，市委是全力以赴，加强领导的","box":[[181,1809],[1692,1833],[1691,1887],[180,1863]]},{"text":"主席革命路线的事命家形象的是材，去们今天的认识，已经不同于","box":[[1954,1824],[3427,1823],[3427,1877],[1954,1878]]},{"text":"党要进一步加强领导，加强创作组力量，抓紧剧本创作，这些","box":[[273,1924],[1678,1953],[1677,2006],[272,1978]]},{"text":"上次会议了，希望检查一下题材，有没有歌颂文化大事命、写坚持","box":[[1957,1941],[3433,1941],[3433,1990],[1957,1990]]},{"text":"重点片，也要准备有些要补拍的，我们部要按主属的指示：不要求","box":[[167,2035],[1678,2066],[1677,2130],[165,2099]]},{"text":"主席車命路线的车命家报露不肯改悔的走资派的趣材，","box":[[1956,2051],[3150,2050],[3150,2104],[1956,2105]]},{"text":"全责备，但大家要按车命样板戏的经验，严格要求，拍得认真严肃，","box":[[161,2151],[1702,2188],[1701,2251],[160,2214]]},{"text":"由影一定要技订划，要有具体的订划，赶前不赶后。","box":[[2065,2163],[3202,2166],[3202,2216],[2065,2213]]},{"text":"要一丝不荷，精益求精，草命的政治内容与尽可能完美的艺术形式","box":[[160,2262],[1677,2306],[1675,2375],[158,2330]]},{"text":"三各厂要批灯光源改革第工作总结汇报一下，还有什么设备","box":[[2058,2280],[3436,2278],[3436,2328],[2058,2329]]},{"text":"相结合，政治质量艺术质量，要尽可能高些，这与一般调滨是有些","box":[[151,2379],[1674,2424],[1672,2493],[149,2448]]},{"text":"上的要求。洪文很关心，最近又有独示，这对增强设备支持很大，","box":[[1960,2397],[3409,2392],[3410,2441],[1960,2447]]},{"text":"—5—","box":[[2622,2510],[2781,2505],[2783,2557],[2623,2562]]},{"text":"—4一","box":[[811,2529],[959,2539],[955,2586],[808,2575]]}],"dimensions":{"height":2700,"width":3600}}