{"ocr_results":[{"text":"第83页，共2743页","box":[[840,51],[1088,53],[1088,76],[840,75]]},{"text":"“你取了手稿怎么不知在哪里？”","box":[[249,162],[603,161],[603,186],[249,187]]},{"text":"“是江青让我们去取的，她可能知道。你们还可以去问原中央文革的工作人","box":[[248,211],[1049,214],[1049,237],[248,235]]},{"text":"员韩书信，他知道。”","box":[[190,261],[428,259],[428,283],[191,286]]},{"text":"“谁让你去取的？”","box":[[248,309],[454,308],[454,333],[248,334]]},{"text":"“江青。她说怕鲁迅的手稿遗失了。”","box":[[249,356],[652,356],[652,383],[249,383]]},{"text":"杨成武和傅崇碧互相对视了一下。江青让威本禹取了手稿，怎么现在义说不","box":[[240,410],[1051,410],[1051,429],[240,429]]},{"text":"知道？这不是贼喊抓贼吗","box":[[188,455],[474,456],[474,480],[188,478]]},{"text":"他们又驱车返回北京，给总理汇报。汇报时江青在场，当然，他们不能说是","box":[[241,508],[1048,508],[1048,527],[241,527]]},{"text":"江青让威本禹取的手稿。只是说韩书信知道。","box":[[190,555],[670,555],[670,575],[190,575]]},{"text":"江青很是恼火，她叫道：“把这个人叫来！”","box":[[236,601],[727,597],[728,625],[236,629]]},{"text":"很不溪巧，这个人回四川休假去了","box":[[241,653],[620,653],[620,673],[241,673]]},{"text":"第四十九章转了一个大弯子","box":[[241,750],[559,750],[559,770],[241,770]]},{"text":"江青指着傅崇碧说：“你马上打电话给成都军区张国华，让他马上把这个人","box":[[241,848],[1048,848],[1048,868],[241,868]]},{"text":"找回来。空军派飞机去接。”","box":[[188,895],[504,894],[504,917],[188,918]]},{"text":"傅崇碧说：“我是一个卫成区司令员，打这个电话不合适。要打，也得请总","box":[[241,945],[1048,945],[1048,965],[241,965]]},{"text":"理、或江青同志打。”","box":[[187,992],[431,989],[431,1014],[187,1016]]},{"text":"江青很不高兴，说：“你这个人，叫你打，你就打嘛，就说是我们说的。”","box":[[239,1041],[1042,1040],[1042,1063],[239,1064]]},{"text":"傅崇碧没有办法，只好去打。","box":[[241,1090],[549,1090],[549,1113],[241,1113]]},{"text":"成都军区对江青的指示不敢总慢，立即派人找到韩书信，并让他连夜乘飞机","box":[[241,1140],[1049,1140],[1049,1160],[241,1160]]},{"text":"回到北京。","box":[[189,1187],[300,1187],[300,1211],[189,1211]]},{"text":"韩书信被送进北京卫成区招待所","box":[[241,1238],[595,1238],[595,1258],[241,1258]]},{"text":"他很是紧张，知道出了事情，肯定事关重大。傅崇碧、周树青等人见到他时","box":[[241,1287],[1045,1287],[1045,1307],[241,1307]]},{"text":"他更加紧张。","box":[[189,1334],[322,1334],[322,1357],[189,1357]]},{"text":"“鲁迅的手稿现在在什么地方？”","box":[[249,1382],[603,1379],[603,1404],[249,1406]]},{"text":"韩书信见问这事，反倒坦然了。他说：“手稿是我取的，取来交给了何先伦","box":[[241,1433],[1047,1433],[1047,1453],[241,1453]]},{"text":"放在什么地方，我不知道。”","box":[[189,1480],[503,1477],[503,1502],[189,1504]]},{"text":"“何先伦在什么地方？”","box":[[248,1528],[501,1523],[502,1551],[248,1556]]}],"dimensions":{"height":1755,"width":1241}}