{"ocr_results":[{"text":"第977页，共2743页","box":[[830,55],[1086,55],[1086,75],[830,75]]},{"text":"命，各个阶级的代表势力都纷纷出来顽强地表现自己，以便让历更对我们进行选","box":[[192,166],[1048,166],[1048,186],[192,186]]},{"text":"择，胜利的胜利得更彻底，跨台的跨台得更痛快","box":[[189,215],[720,215],[720,235],[189,235]]},{"text":"党内一小振走资派同广大工农兵革命干部革命知识分子的矛盾是主要矛盾，","box":[[241,264],[1045,264],[1045,284],[241,284]]},{"text":"解决这个主要的矛盾是无产阶级和资产阶级两个阶级的斗争，社会主义和资本主","box":[[190,313],[1051,313],[1051,333],[190,333]]},{"text":"义两条道路的斗争的集中表现，这是问题的本质。另一方面，无产阶级文化大革","box":[[193,361],[1049,361],[1049,380],[193,380]]},{"text":"命对于广大工农兵群众和大多数人来说是个新课题，工人运动不会自发地产生马","box":[[189,407],[1049,408],[1049,432],[189,431]]},{"text":"克思列宁主义和毛泽东思想，马克思列宁主义和毛泽东思想需要从外部向工农群","box":[[192,459],[1051,459],[1051,478],[192,478]]},{"text":"众灌输。这个灌输的过程是少数教育多数的过程，也是群众自己教育自己，重新","box":[[190,508],[1049,508],[1049,527],[190,527]]},{"text":"学习如何在无产阶级这个新的历史条件下进行革命的过程，在这个学习的过程","box":[[189,554],[1035,554],[1035,578],[189,578]]},{"text":"中，一部分会受蒙蔽，会犯这样那样的错误，因此在无产阶级和其他劳动群众内","box":[[190,604],[1048,604],[1048,624],[190,624]]},{"text":"部也会有先进和后进的矛盾。","box":[[192,653],[496,653],[496,673],[192,673]]},{"text":"毛主席在《再论无产阶级专政历史经验》一文中正确指出，有时为了对付主","box":[[241,702],[1049,702],[1049,722],[241,722]]},{"text":"要的共同的敌人，利害根本冲突的阶级也可以联合起来。反之，在特定的情况下","box":[[190,749],[1049,750],[1049,771],[190,770]]},{"text":"人民内部的某种矛盾，由于矛盾一方面转化为对抗性的矛盾。","box":[[192,799],[848,799],[848,819],[192,819]]},{"text":"于是文化大革命出现了这样的复杂情况：一方面我们的主要敌人党内军内一","box":[[241,848],[1052,848],[1052,868],[241,868]]},{"text":"小摄走资派利用运动中的次要矛盾，比如人民群众中先进和落后的矛盾，工农兵","box":[[192,897],[1051,897],[1051,917],[192,917]]},{"text":"和他们的次要敌人即地富反坏右的矛盾来拖盖运动的主要矛盾，转移群众斗争大","box":[[190,945],[1052,945],[1052,965],[190,965]]},{"text":"方向，以图保护自己。有时他们利用“造反派”队伍特别是团派的队伍不纯挑动","box":[[188,993],[1051,992],[1051,1015],[188,1016]]},{"text":"受蒙蔽群众去镇压“造反派”首先是“团派”。有时他们则通过无原则的吹捧利","box":[[188,1042],[1051,1041],[1051,1064],[188,1065]]},{"text":"用团派中的“极左势力”炮打无产阶级司令部，打击所请“右倾势力”的四一四","box":[[190,1092],[1049,1092],[1049,1112],[190,1112]]},{"text":"派，特别是参加过保守势力的曾受蒙蔽的群众，破坏革命的大联合，等等，等等。","box":[[189,1139],[1049,1139],[1049,1162],[189,1162]]},{"text":"归根到底，激化次要矛盾的目的是为了保护他手中的大权，并且有朝一日利用他","box":[[190,1189],[1048,1189],[1048,1209],[190,1209]]},{"text":"们手中的政权将中国引向资本主义。","box":[[192,1238],[571,1238],[571,1258],[192,1258]]},{"text":"另一方面，我们的次要敌人，一些资产阶级份子，地富反环右及其代表他们","box":[[239,1286],[1051,1285],[1051,1308],[239,1309]]},{"text":"利益的知识分子顽强地活动起来，他们自觉不自觉地混入了造反派的队伍（主要","box":[[190,1336],[1049,1336],[1049,1356],[190,1356]]},{"text":"是团派）他们表现得“极左”，对财产和权力的“再分配”要求最道切，他们咬","box":[[192,1385],[1049,1385],[1049,1405],[192,1405]]},{"text":"牙切齿要想一棍子把受蒙蔽的工农群众打成“保守阶级”，而他们自己则成为压","box":[[189,1434],[1051,1434],[1051,1454],[189,1454]]},{"text":"道“保守阶级”的“造反阶级”他们仿佛也在革命的航船上划浆，但是他们的目","box":[[189,1483],[1048,1483],[1048,1503],[189,1503]]},{"text":"的是把船撞到暗上，以便来个阶级关系“大翻个儿”复解资本主义。当然，他","box":[[192,1531],[1049,1531],[1049,1551],[192,1551]]}],"dimensions":{"height":1755,"width":1241}}