{"ocr_results":[{"text":"百","box":[[7,532],[93,537],[85,674],[0,669]]},{"text":"上，他强调要借用俄语语汇，反对借用汉语语汇，胡说借用汉语","box":[[432,562],[2299,653],[2295,744],[428,653]]},{"text":"的","box":[[11,651],[92,651],[92,753],[11,753]]},{"text":"“太快了”“太多了”，要“慢慢来”。在维语文字改革时，他反","box":[[456,690],[2331,773],[2327,864],[452,782]]},{"text":"中","box":[[21,719],[85,726],[77,809],[12,802]]},{"text":"自","box":[[8,777],[81,777],[81,893],[8,893]]},{"text":"对周总理关于“汉字改革要采用拉了字母，各少数民族文字改革也","box":[[432,822],[2320,894],[2317,985],[428,913]]},{"text":"","box":[[8,930],[86,930],[86,1008],[8,1008]]},{"text":"要采用拉丁字母”的指示，顽固坚持用斯拉大字母。由千广大干","box":[[426,951],[2323,1017],[2320,1108],[423,1042]]},{"text":"部、群众的抵制和反对，最后被追改了回来，使新疆文字改革走了","box":[[426,1088],[2320,1137],[2318,1229],[423,1179]]},{"text":"发","box":[[4,1199],[72,1206],[63,1289],[0,1282]]},{"text":"一段很大的变路。","box":[[433,1225],[924,1236],[922,1309],[431,1297]]},{"text":"公","box":[[5,1351],[68,1351],[68,1415],[5,1415]]},{"text":"11、解放初期，赛福鼎反对党对原三区革命的民族军的整编，","box":[[554,1359],[2301,1386],[2299,1475],[553,1447]]},{"text":"反对党派政工干部去民族军工作。党派到民族军的干部、政治指导","box":[[422,1493],[2355,1507],[2354,1603],[421,1590]]},{"text":"员只能叫政治干事，只能搞教唱歌等文娱工作。一九五0年，赛曾","box":[[427,1633],[2354,1635],[2354,1727],[427,1724]]},{"text":"内","box":[[3,1775],[62,1775],[62,1844],[3,1844]]},{"text":"向彭德怀提出要增加民族军的编制，扩充民族军。还提出，由民族军","box":[[424,1772],[2365,1767],[2365,1850],[424,1855]]},{"text":"约","box":[[0,1917],[59,1917],[59,1989],[0,1989]]},{"text":"驻守城市，边防军只驻国境线上。由于他的阻控，民族军改编为五","box":[[421,1917],[2370,1898],[2371,1970],[422,1989]]},{"text":"军的问题拖到一九五二年才解决。他还亲白在五军军部设立了一个","box":[[426,2057],[2370,2026],[2371,2099],[427,2129]]},{"text":"控告党的干部的“接待室”，把一些反革命分子释放出来。","box":[[429,2199],[2140,2158],[2142,2230],[430,2271]]},{"text":"中","box":[[3,2212],[43,2212],[43,2281],[3,2281]]},{"text":"","box":[[14,2233],[32,2233],[32,2265],[14,2265]]},{"text":"12、一九五七年七、八月间，赛看到有的汉族干部也到南山游","box":[[555,2341],[2391,2286],[2393,2356],[558,2411]]},{"text":"览，就借机攻击说：“这些人现在都喜欢上山了。看来，他们起初","box":[[423,2483],[2401,2412],[2404,2492],[426,2564]]},{"text":"中","box":[[5,2525],[38,2525],[38,2579],[5,2579]]},{"text":"对任何事情好象不发生兴趣，可是等到有了兴趣之后，那简直象发","box":[[420,2628],[2412,2548],[2415,2629],[423,2709]]},{"text":"疯的一般。有个比方，蒙古人的马不吃料，一旦吃了料，马拉横","box":[[417,2773],[2427,2680],[2431,2768],[421,2862]]},{"text":"类。他们就这样，…···。”","box":[[417,2923],[1248,2886],[1251,2967],[421,3004]]},{"text":"西","box":[[5,2984],[38,2984],[38,3037],[5,3037]]},{"text":"13、一九六七年，赛接见由地方民族主义分子操纵的组织“三","box":[[560,3066],[2432,2966],[2437,3047],[565,3146]]},{"text":"连”的头头，并煸动说，“我骑在一匹马上，但马的细绳不在我手","box":[[420,3218],[2440,3106],[2445,3189],[424,3302]]},{"text":"1","box":[[5,3287],[38,3287],[38,3348],[5,3348]]},{"text":"中。”意思是说他没有权","box":[[425,3374],[1226,3331],[1230,3403],[429,3446]]},{"text":"29","box":[[2263,3410],[2338,3410],[2338,3480],[2263,3480]]},{"text":"校","box":[[11,3458],[30,3458],[30,3477],[11,3477]]}],"dimensions":{"height":3024,"width":4032}}