{"ocr_results":[{"text":"L","box":[[2583,314],[2635,314],[2635,359],[2583,359]]},{"text":"不是以实事求是的态度来搞新闻报道，不认真学习毛主席的各项指示，也不进行","box":[[173,359],[1981,339],[1981,383],[173,403]]},{"text":"公","box":[[2585,357],[2631,357],[2631,397],[2585,397]]},{"text":"深入的调查研究，只是坐在上面想点子，跑到下面找例子，关起门来写稿子，一","box":[[171,453],[1984,436],[1984,480],[172,497]]},{"text":"作","box":[[2585,484],[2630,484],[2630,524],[2585,524]]},{"text":"请","box":[[2581,532],[2631,532],[2631,579],[2581,579]]},{"text":"味“笔下生花”，甚至采取资产阶级庸俗的手段，任意添枝加叶，就不能正确反映客","box":[[171,549],[1984,530],[1984,574],[172,593]]},{"text":"重","box":[[2582,611],[2629,611],[2629,653],[2582,653]]},{"text":"观事物，就不能体现毛主席的路线和政策，就不能给人以正确的认识，就会危害","box":[[175,643],[1983,623],[1984,667],[176,687]]},{"text":"作","box":[[2583,650],[2629,650],[2629,692],[2583,692]]},{"text":"者","box":[[2583,690],[2630,690],[2630,732],[2583,732]]},{"text":"革命事业，背离毛主席的新闻路线。正确的典型和口号可以给实际工作以很大的","box":[[178,735],[1986,719],[1987,764],[178,780]]},{"text":"版","box":[[2585,730],[2631,730],[2631,776],[2585,776]]},{"text":"权","box":[[2585,771],[2630,771],[2630,811],[2585,811]]},{"text":"帮助，而不正确的典型和口号也会给实际工作带来很大的妨碍，决不可以掉以轻","box":[[181,832],[1988,814],[1988,858],[181,876]]},{"text":"心，兴之所至，任意发挥，不讲政策；决不能为了追求情节生动，违反事实。因","box":[[182,926],[1986,909],[1987,954],[182,972]]},{"text":"此，是不是以实事求是的态度来搞新闻报道，决不是一般的问题，而是有没有无产","box":[[182,1022],[1988,1005],[1988,1050],[182,1067]]},{"text":"阶级党性或党性纯不纯的问题，是执行不执行毛主席无产阶级新闻路线的问题。","box":[[183,1119],[1962,1103],[1963,1143],[184,1159]]},{"text":"新闻报道工作要实事求是，但不等于就事论事，只停留在事物的表面现象。","box":[[288,1209],[1990,1195],[1991,1238],[289,1253]]},{"text":"毛主席教导我们：““实事”就是客观存在着的一切事物，‘是”就是客观事物的内部","box":[[185,1305],[1994,1289],[1995,1334],[185,1350]]},{"text":"联系，即规律性，“求”就是我们去研究。”（《改造我们的学习》）新闻报道工作，应当从","box":[[183,1398],[1993,1382],[1993,1432],[184,1449]]},{"text":"客观存在着的实际事物出发，详细占有材料，加以科学分析，从中找出规律性的东","box":[[186,1495],[1992,1478],[1992,1521],[186,1539]]},{"text":"西，帮助人民拿了这种对于客观规律性的认识，能动地改造世界。一、二、三、四罗","box":[[189,1586],[1993,1572],[1993,1621],[189,1635]]},{"text":"列现象和材料而不加以选择和分析，只能使文章兄长，决不能成为好报道。我们","box":[[190,1684],[1998,1668],[1999,1712],[190,1728]]},{"text":"反对浮夸拔高，但决不等于不要加工提高。所谓加工提高，就是“经过思考作用，将","box":[[189,1778],[1997,1763],[1997,1807],[189,1822]]},{"text":"丰富的感觉材料加以去粗取精、去伪存真、由此及彼、由表及里的改造制作工夫”，","box":[[189,1873],[1992,1858],[1992,1903],[189,1918]]},{"text":"从感性认识提高到理性认识，更深刻、更正确，更完全地反映客观事物。","box":[[190,1971],[1813,1957],[1814,1999],[190,2012]]},{"text":"有什么样的世界观，就会执行什么样的路线。只有树立辩证唯物主义和历史","box":[[296,2065],[1997,2049],[1997,2089],[297,2105]]},{"text":"唯物主义的世界观，才能具有为无产阶级政治服务的方向，相信群众，依靠群众的","box":[[195,2161],[1998,2143],[1999,2183],[196,2201]]},{"text":"正确态度，战斗的、实事求是的工作作风，才能有高度的执行毛主席无产阶级新","box":[[195,2254],[1997,2238],[1997,2279],[196,2295]]},{"text":"闻路线的自觉性。每个新闻报道人员都要认真刻苦她活学活用毛泽东思想，深入","box":[[191,2344],[1999,2328],[2000,2377],[192,2394]]},{"text":"开展革命大批判，肃清刘少奇反革命修正主义新闻路线的余毒。要坚持参加集体","box":[[194,2444],[2001,2428],[2001,2472],[194,2488]]},{"text":"生产劳动，密切联系群众，在三大革命运动的实践中，促进思想革命化。各级领","box":[[191,2538],[2004,2522],[2004,2566],[192,2582]]},{"text":"导要认真对从事新闻报道工作的同志进行思想和政治路线方面的教育，使我们的","box":[[198,2633],[2001,2615],[2001,2655],[198,2673]]},{"text":"新闻报道队伍沿着毛主席的无产阶级革命路线胜利前进！","box":[[197,2719],[1458,2712],[1459,2757],[197,2764]]},{"text":"（总97）·11","box":[[1740,2827],[1999,2822],[2000,2862],[1741,2867]]},{"text":"1971年第2期","box":[[197,2837],[486,2841],[485,2881],[197,2877]]},{"text":"y","box":[[84,3207],[146,3207],[146,3257],[84,3257]]}],"dimensions":{"height":3317,"width":2638}}