{"ocr_results":[{"text":"宜黄乐安等地敌情和我军作战部署叫","box":[[45,69],[370,65],[370,85],[45,89]]},{"text":"（1932年8月15日）","box":[[152,101],[264,101],[264,113],[152,113]]},{"text":"中央局，并转中央","box":[[33,191],[130,191],[130,202],[33,202]]},{"text":"（一）北向行动方针乃见前电”。红一方面军已于十五日到达招","box":[[55,212],[383,211],[383,222],[55,223]]},{"text":"携、东韶一带。","box":[[32,234],[113,234],[113,245],[32,245]]},{"text":"（二）敌情：孙连仲“部一师分驻宜黄、乐安，一师驻崇仁、抚","box":[[54,255],[384,254],[384,266],[54,267]]},{"text":"州：朱绍良部毛师在南丰，李师在南城，许师在其中：吴奇","box":[[32,277],[383,276],[383,287],[32,288]]},{"text":"伟师一旅在永丰，一旅在吉水、吉安，一旅在樟树、新干：陈","box":[[33,298],[384,297],[384,309],[33,310]]},{"text":"[1]这是毛泽东和周思来、朱德、红军第一方而军总政治部主任王惊祥","box":[[50,345],[385,343],[385,356],[50,357]]},{"text":"给中共苏区中央局并转中央的电报","box":[[32,361],[192,362],[192,374],[32,372]]},{"text":"2]","box":[[51,381],[64,381],[64,392],[51,392]]},{"text":"即《当前作战方向问题》","box":[[73,381],[187,381],[187,391],[73,391]]},{"text":"3]","box":[[50,398],[64,398],[64,411],[50,411]]},{"text":"招携，位于江西乐安县南部。东韶，位于江西宁都县北部。","box":[[74,398],[340,398],[340,408],[74,408]]},{"text":"14","box":[[50,415],[64,415],[64,428],[50,428]]},{"text":"孙连仲，当时任国民党军赣粤间边区“剩”总司令部第九路司令官。","box":[[73,416],[379,415],[379,425],[73,426]]},{"text":"15]","box":[[50,433],[65,433],[65,446],[50,446]]},{"text":"朱绍良，当时任国民党军粤间边区“别题”总罚令部第六路司令官。","box":[[73,434],[380,433],[380,443],[73,444]]},{"text":"6","box":[[51,451],[64,451],[64,462],[51,462]]},{"text":"毛师，指国民党军费导间边区“别”总司令部第六路第八师，师","box":[[74,452],[384,451],[384,461],[74,462]]},{"text":"长毛炳文。","box":[[33,466],[77,469],[77,480],[32,478]]},{"text":"7李师，指国民党军赣粤同边区“剩匯”总司令部第六路第二十三","box":[[50,485],[385,485],[385,499],[50,499]]},{"text":"师，师长李云杰。","box":[[33,501],[109,506],[108,517],[33,512]]},{"text":"[8]许师，指国民党军粤间边区“别”总司令部第六路第二十四","box":[[51,521],[385,521],[385,534],[51,533]]},{"text":"师，师长许充拼。","box":[[34,536],[110,541],[109,552],[33,547]]},{"text":"[9]吴奇伟师，指国民党军粤间边区“剩匯”总司令部第二路第九十","box":[[51,555],[384,557],[384,570],[51,568]]},{"text":"师，师长吴奢伟。","box":[[34,571],[110,576],[109,588],[34,582]]},{"text":"95","box":[[374,595],[388,595],[388,608],[374,608]]}],"dimensions":{"height":623,"width":454}}