{"ocr_results":[{"text":"化、消极意工、官主义工作方式的分子，当选为执行委员。在选","box":[[59,56],[411,55],[411,66],[59,67]]},{"text":"举执行委员会时，要特别注意工人模极分子，要将这样的分子大量","box":[[59,78],[410,77],[410,87],[59,88]]},{"text":"地选举到执行委员会去，加强无产阶级在苏维埃中的领导力量。同","box":[[58,100],[412,99],[412,109],[58,110]]},{"text":"时对于贫农中农的积极分子，要有很好的注意与吸收。并且不要忘","box":[[59,122],[411,121],[411,131],[59,132]]},{"text":"记了选举劳动妇支到苏维块工作，执行委员之中，劳动妇安至少要","box":[[59,144],[411,143],[411,153],[60,154]]},{"text":"时额注意工作能力，决不能只看成分，不看工作能力如何，随便列","box":[[58,187],[411,186],[411,196],[58,197]]},{"text":"入名单。执行委员选出之后，须报售上级执行委员会审查批准。","box":[[59,209],[411,208],[411,218],[59,219]]},{"text":"（四）关于政府简选民及代表大会作工作报告，必须在这次选举运动","box":[[60,231],[411,230],[411,240],[60,241]]},{"text":"中真正地实行起来。过去除一部分地方外，多数地方没有实行，是","box":[[59,252],[412,251],[412,261],[60,262]]},{"text":"不对的。这一办法的实行，能使政府的政策与工作，在群众中得到","box":[[59,274],[411,273],[411,283],[59,284]]},{"text":"检验的机会，能便选民对于选举的热忧提到更高的程度。实行的办","box":[[59,296],[410,294],[410,304],[60,306]]},{"text":"法是：乡苏市苏在选举之前一星期，以屋子或村子为单位召集选民","box":[[59,317],[410,316],[410,327],[59,328]]},{"text":"大会，作总结乡苏市苏过去的尤其是最近一个时期的工作经过的推","box":[[59,339],[410,338],[410,348],[59,350]]},{"text":"告，发动选民群众的批评与讨论，欢迎他们提出新的具体的意见","box":[[59,361],[410,359],[410,369],[60,372]]},{"text":"以为政府以后工作的方针。区政府须在各乡苏和市苏的全体代表会","box":[[59,382],[410,380],[411,392],[59,394]]},{"text":"议上作工作报告，并吸收广大群众来参加旁听，乡苏市苏的代表会","box":[[59,404],[410,401],[411,413],[60,416]]},{"text":"议，对于区苏的工作报告，须作详细的讨论，将讨论结果提到区政","box":[[59,426],[412,423],[412,435],[59,438]]},{"text":"府去。县政府则派代表到区苏代表大会作工作报告。省政府则派代","box":[[58,447],[411,444],[411,457],[58,460]]},{"text":"表到县苏代表大会作工作报告。中央政府则到省苏代表大会作工作","box":[[59,469],[411,466],[411,479],[59,482]]},{"text":"报告。同时在各级代表大会上，本级的执行委员会须向之作同样的","box":[[58,490],[411,487],[411,501],[58,504]]},{"text":"报告。在这些报告之后，都须经过详细讨论，将讨论结果，按级报","box":[[58,512],[412,508],[412,522],[58,527]]},{"text":"告上级政府。要将群众对于政府工作的意见，一直达到中央政府","box":[[58,534],[412,529],[412,545],[58,550]]},{"text":"来，使苏维埃的最高机关了解群众的情绪与要求。各级政府对于自","box":[[58,555],[411,550],[411,566],[58,571]]},{"text":"已的工作报告，须事先指定专人起草。中央内务人民委员部应拟出","box":[[58,577],[412,572],[412,587],[58,592]]},{"text":"354","box":[[56,608],[77,608],[77,619],[56,619]]}],"dimensions":{"height":635,"width":452}}