{"books":[{"id":"CCRD-shzygz","name":"中国五十年代初中期的政治运动数据库","internal":false,"official":false,"type":"db","author":"宋永毅","files":[""],"article":{"title":"毛泽东关于处理涉及重要民主人士及其戚友的案件的批语","authors":["毛泽东"],"dates":[{"year":1951,"month":6,"day":3}],"is_range_date":false,"parts":[{"text":"毛泽东关于处理涉及重要民主人士及其戚友的案件的批语","type":"title"},{"text":"毛泽东","type":"authors"},{"text":"罗瑞卿同志：","type":"appellation"},{"text":"凡关涉重要民主人士及其戚友的案件，只收集材料，不忙处理。","type":"paragraph"},{"text":" 毛泽东六月三日","type":"paragraph"}],"comments":[],"origin":"","comment_pivots":[],"description":"","page_start":0,"page_end":0,"alias":""},"tags":[{"name":"毛泽东","type":"人物"},{"type":"文稿类型","name":"批示"}]}]}