{"ocr_results":[{"text":"论持久战","box":[[489,177],[675,177],[675,204],[489,204]]},{"text":"431","box":[[970,179],[1012,179],[1012,206],[970,206]]},{"text":"（三六）第-一阶段，现存还未完结。敌之企图是攻占广州、","box":[[198,251],[1037,254],[1037,283],[198,280]]},{"text":"武汉、兰州三点，并把三点联系起来。敌欲达此目的，至少出","box":[[125,302],[1037,303],[1037,333],[125,332]]},{"text":"五十个师留，约一百五十万兵员，时间一年半至两年，用费将","box":[[125,355],[1036,355],[1036,382],[125,382]]},{"text":"在一百万万日元以上。敌人如此深入，其困难是非常之大的，","box":[[123,406],[1032,406],[1032,433],[123,433]]},{"text":"其后果将不堪设想。至欲之全占领粤汉铁路和西兰公路，将","box":[[121,455],[1035,457],[1035,484],[121,483]]},{"text":"经历非常危险的战争，未必尽能达其企图。但是我们的作战","box":[[120,505],[1034,507],[1034,534],[120,532]]},{"text":"计划，应把敌人可能占领三点甚至三点以外之某些部分地区","box":[[120,554],[1032,557],[1032,584],[120,581]]},{"text":"并可能互相联系起来作为一种基础.部署持久战，即令敌如此","box":[[119,603],[1032,607],[1032,635],[119,630]]},{"text":"做，我也有应付之方。这-阶段我所采取的战争形式，主要的","box":[[119,654],[1030,656],[1030,684],[119,682]]},{"text":"是运动战，而以游击战和阵地战辅助之。阵地战虽在此阶段","box":[[117,704],[1030,706],[1030,733],[117,731]]},{"text":"之第一期，由于国民党军事当局的主观错误把它放在主要地","box":[[114,752],[1028,754],[1028,784],[114,782]]},{"text":"位，但从全阶段看，仍然是辅助的。此阶段中，中国已经结成","box":[[115,802],[1027,806],[1027,834],[115,830]]},{"text":"了广大的统一战线、实现了空前的闭结。敌虽已经采用过并","box":[[116,852],[1026,856],[1026,884],[116,880]]},{"text":"且还将采用卑鄙无耻的劝降手段，企图不费大力实现其速决","box":[[112,901],[1026,905],[1026,935],[112,931]]},{"text":"计划，整个地征服中国·但是过去的己经失败，今后的也难成","box":[[113,952],[1024,957],[1024,984],[113,979]]},{"text":"功。此阶段中，中国虽有颇大的损失，但是同时却有颇大的进","box":[[112,1001],[1022,1007],[1022,1034],[112,1029]]},{"text":"步，这种进步就成为第二阶段继续抗战的主要基础。此阶段","box":[[111,1051],[1022,1057],[1022,1084],[111,1078]]},{"text":"中，苏联对于我国记经有了大量的援助，敌人方面，士气已开","box":[[110,1101],[1020,1107],[1020,1133],[110,1127]]},{"text":"始表现颜靡，敌人陆军进攻的锐气，此阶段的中期已不如初期，","box":[[109,1149],[1020,1155],[1020,1183],[109,1176]]},{"text":"末期将更不如初期，敌之财政和经济已开始表现其竭状态，","box":[[108,1200],[1019,1205],[1019,1232],[108,1227]]},{"text":"人民和士兵的厌战情绪已开始发生，战争指导集团的内部已","box":[[106,1248],[1018,1253],[1018,1283],[106,1278]]},{"text":"开始表现其“战争的烦闷”，生长着对于战争前途的悲观。","box":[[107,1300],[944,1303],[944,1333],[107,1330]]},{"text":"（三七）第二阶段，可以名之日战略的相持阶段。第一阶","box":[[179,1353],[1015,1352],[1015,1383],[179,1384]]},{"text":"段之末尾，由于敌之兵力不足和我之坚强抵抗，敌人将不得不","box":[[108,1404],[1017,1403],[1017,1433],[108,1434]]},{"text":"决定在一定限度上的战略进攻终点，到达此终点以后，即停止","box":[[110,1455],[1015,1455],[1015,1482],[110,1482]]}],"dimensions":{"height":1641,"width":1152}}