{"ocr_results":[{"text":"GG","box":[[115,105],[143,105],[143,124],[115,124]]},{"text":"第三篇社会总资本的再生产和流通","box":[[269,106],[539,106],[539,123],[269,123]]},{"text":"变资本，而不必为此先出售他的剩余产品；同样地，他能够直接把","box":[[97,164],[717,164],[717,181],[97,181]]},{"text":"它转化为不变资本的要素。但是在后一种场合，他就必须找到不","box":[[97,200],[718,199],[718,218],[97,219]]},{"text":"变资本的各种物质要素；或者象以上说明的那样，假定每个生产者","box":[[98,239],[717,239],[717,255],[98,255]]},{"text":"都是为存货而生产，然后把他的成品送往市场，或者假定每个生产","box":[[97,275],[718,273],[718,292],[97,294]]},{"text":"者都是为订货而生产。在这两个场合，都是以生产的实际扩大为","box":[[97,314],[717,312],[717,329],[98,331]]},{"text":"前提的，也就是以剩余产品为前提的；在前一个场合，剩余产品是","box":[[98,350],[717,350],[717,367],[98,368]]},{"text":"实际存在的，在后一个场合，剩余产品是潜在地存在的，是能够供","box":[[98,388],[717,386],[717,403],[98,405]]},{"text":"应的。","box":[[96,421],[151,424],[150,445],[96,443]]},{"text":"I1.第I部类的积累","box":[[288,538],[523,538],[523,561],[288,561]]},{"text":"以上我们假定，A、A、A”（I）是把他们的剩余产品卖给也","box":[[143,611],[717,611],[717,630],[143,631]]},{"text":"是属于第I部类的B、B、B\"等等。现在我们假定，A（I）把他","box":[[99,650],[718,650],[718,669],[99,669]]},{"text":"的剩余产品转化为货币，是由于把剩余产品卖给第II部类的B","box":[[100,688],[714,688],[714,705],[100,706]]},{"text":"这种情况所以能够发生，只是因为A（1）把生产资料卖给B（1I）","box":[[98,727],[716,725],[716,742],[98,744]]},{"text":"以后，不接着购买消费资料，也就是说，只是因为他这方面进行的","box":[[100,764],[717,763],[717,780],[100,781]]},{"text":"是单方面的卖。IIc所以能够由商品资本的形式转化为不变生产","box":[[97,800],[719,799],[719,819],[98,820]]},{"text":"资本的实物形式，只是因为不仅I，而且至少Im的一部分，和","box":[[97,838],[719,837],[719,857],[97,857]]},{"text":"以消费资料形式存在的IIc的一部分相交换；而现在，A把他","box":[[99,876],[719,875],[719,895],[99,896]]},{"text":"的Im转化为货币，是由于这种交换没有进行，相反地，A把通过","box":[[99,914],[719,912],[719,931],[99,933]]},{"text":"出售他的Im而从第I部类得到的货币从流通中取出，不用它来","box":[[101,951],[718,949],[718,968],[101,970]]},{"text":"购买消费资料IIc。因此，在A（I）方面虽然形成追加的潜在货","box":[[97,988],[719,986],[719,1006],[98,1008]]},{"text":"币资本；但是另一方面，B（I）却有同等价值量的一部分不变资","box":[[100,1026],[719,1024],[719,1043],[100,1046]]},{"text":"本，被凝结在商品资本的形式上，不能够转化为不变生产资本的实","box":[[97,1065],[720,1062],[720,1081],[98,1084]]}],"dimensions":{"height":1246,"width":865}}