{"ocr_results":[{"text":"820","box":[[126,112],[150,112],[150,129],[126,129]]},{"text":"第六篇超额利润转化为地租","box":[[298,112],[507,112],[507,129],[298,129]]},{"text":"B级土地第一次2六榜的投资每英亩产生2夸特，第二次同","box":[[143,164],[702,166],[702,189],[143,186]]},{"text":"样大的投资每英亩产生1","box":[[104,201],[347,203],[347,224],[104,222]]},{"text":"夸特；在同--英亩上合计产生3夸","box":[[342,201],[702,201],[702,228],[342,228]]},{"text":"特。就这个从同一土地产生的3夸特来看，看不出其中哪一部","box":[[101,236],[704,237],[704,264],[101,262]]},{"text":"分是第一次投资的产物，哪一部分是第二次投资的产物。事实上，","box":[[102,274],[698,275],[698,295],[102,294]]},{"text":"它们是总资本5榜的产物；实际情况只是，一个2÷镑的资本产生","box":[[103,309],[701,309],[701,333],[103,333]]},{"text":"2夸特，一个5镑的资本却不是产生4夸特，而是产生3一夸特。即","box":[[99,346],[700,345],[700,369],[99,370]]},{"text":"使5榜产生4夸特，从而两个投资的产量相等，或者甚至产生5夸","box":[[102,385],[699,386],[699,404],[102,403]]},{"text":"特，从而第二次投资产生1夸特的余额，情形也完全一样。前2夸","box":[[101,419],[699,421],[699,441],[101,439]]},{"text":"特的生产价格是每夸特1榜，后1夸特的生产价格是每夸特2","box":[[100,455],[701,456],[701,480],[100,479]]},{"text":"镑。因此3夸特总计的费用是6镑。这是总产品的个别生产价","box":[[98,489],[700,490],[700,520],[98,519]]},{"text":"格，平均计算是每夸特1榜14亏先令，就是说约为1镑。按A级","box":[[99,528],[698,529],[698,553],[99,552]]},{"text":"土地决定的一般生产价格3镑计算，每夸特会产生超额利润1","box":[[98,558],[698,564],[698,593],[98,588]]},{"text":"镑，3夸特合计会产生4镑。按B级土地的平均生产价格计","box":[[99,600],[699,600],[699,627],[99,627]]},{"text":"算，这个数目就体现在约1夸特中。所以，B级土地的超额利","box":[[97,637],[698,636],[698,662],[97,663]]},{"text":"润体现在B的一部分产品中，即1六夸特中，而这就是以谷物来表","box":[[99,674],[697,674],[697,697],[99,697]]},{"text":"现的地租；按一般生产价格计算，这些谷物要卖4六镑。但是相反","box":[[91,711],[695,710],[695,732],[91,733]]},{"text":"地，B级土地一英亩多于A级土地一英亩的超额产品，并不无条","box":[[100,749],[693,749],[693,766],[100,766]]},{"text":"件就是超额利润的表现，因此也不是无条件就是剩余产品的表现。","box":[[100,786],[692,786],[692,802],[100,802]]},{"text":"按照假定，B级土地每英亩生产3夸特，A级土地每英亩只生产","box":[[97,819],[696,818],[696,842],[97,843]]},{"text":"1夸特。所以,B 级土地一英亩的超额产品是2夸特，但剩余产","box":[[92,853],[697,853],[697,886],[92,886]]},{"text":"品却只是1夸特；因为B级土地上的投资，比A级土地上的投资","box":[[97,891],[694,891],[694,918],[97,918]]},{"text":"多一倍，生产费用也多一倍。如果A级土地同样有5榜投资：生产","box":[[99,931],[692,931],[692,947],[99,947]]},{"text":"率不变，它的产品就是2夸特，而不是1夸特，由此可见，实际的剩","box":[[99,967],[692,967],[692,984],[99,984]]},{"text":"余产品，并不是由3和1比较，而是由3和2比较得出来的。","box":[[95,998],[693,1000],[693,1027],[95,1025]]},{"text":"所以，剩余产品不是2夸特，而只是1六夸特。其次，如果B级","box":[[97,1037],[693,1037],[693,1060],[97,1060]]}],"dimensions":{"height":1200,"width":817}}