{"ocr_results":[{"text":"第3144页，共5150页","box":[[818,55],[1086,55],[1086,75],[818,75]]},{"text":"一、中央关于不得把斗争锋芒指向军队的通知稿。","box":[[241,166],[769,166],[769,186],[241,186]]},{"text":"","box":[[778,170],[800,170],[800,180],[778,180]]},{"text":"通知福写道，人民解","box":[[832,166],[1051,166],[1051,186],[832,186]]},{"text":"放军是无产阶级专政的最主要的工具，它担负看备战和保卫国防的伟大任务，担","box":[[192,215],[1049,215],[1049,235],[192,235]]},{"text":"负看保卫无产阶级文化大革命的伟大任务。任何人、任何组织，都不得冲击人民","box":[[192,264],[1049,264],[1049,284],[192,284]]},{"text":"解放军的机关。有一些地方党委，借保证党和国家机密安全及党内文电正常传递","box":[[190,313],[1051,313],[1051,333],[190,333]]},{"text":"为名，把文化大革命中整革命群众的材料塞进军事机关，甚至挑动不明真相的群","box":[[190,361],[1049,361],[1049,380],[190,380]]},{"text":"众把斗争锋芒指向军事机关，这是极端错误的，是党纪国法绝不允许的。一九六","box":[[190,410],[1049,410],[1049,429],[190,429]]},{"text":"七年一月十四日，中共中央下发了这个通知","box":[[192,459],[670,459],[670,478],[192,478]]},{"text":"二、中央、国务院关于在无产阶级文化大革命中加强公安工作的若十规定稿","box":[[241,508],[1047,508],[1047,527],[241,527]]},{"text":"规定稿指出：“公安机关是无产阶级专政的重要工具之一，必须适应无产阶级文","box":[[190,555],[1049,555],[1049,575],[190,575]]},{"text":"化大革命形势发展的需要，采取恰当的方式，加强对故人的专政，保障人民的民","box":[[192,604],[1049,604],[1049,624],[192,624]]},{"text":"主权利，保障大鸣、大放、大字报、大辩论、大串连的正常进行，保障无产阶级","box":[[190,653],[1049,653],[1049,673],[190,673]]},{"text":"的革命秩序。”为此，作出依法惩办现行反革命分子等六项具体规定。一九六七","box":[[192,702],[1051,702],[1051,722],[192,722]]},{"text":"年一月十三日，中共中央、国务院下发了这个规定。","box":[[188,748],[746,749],[746,772],[188,771]]},{"text":"三、中央军委一九六七年一月七日关于重申军队绝不允许当防空洞的通知","box":[[240,799],[1034,799],[1034,819],[240,819]]},{"text":"稿。通知稿指出：“无产阶级文化大革命以来，我们曾三令五申，军队（包括医","box":[[187,847],[1049,846],[1049,869],[187,871]]},{"text":"院、疗养院、招待所等）决不能成为防空洞，窝藏一小振党内走资本主义道路的","box":[[189,896],[1049,895],[1049,918],[189,920]]},{"text":"当权派，底护那些坚持执行资产阶级反动路线的以及逃避群众斗争的人。但是，","box":[[189,943],[1044,944],[1044,967],[189,966]]},{"text":"至今仍然有一些单位没有这样做，甚至有的参与了压制、打击和镇压革命群众的","box":[[189,993],[1049,994],[1049,1015],[189,1014]]},{"text":"行动。”“各级党委对此必须引起严重注意，立即采取坚决措施，杜绝类似情况","box":[[189,1041],[1049,1041],[1049,1064],[189,1064]]},{"text":"的继续发生。”","box":[[188,1090],[356,1087],[356,1112],[188,1115]]},{"text":"","box":[[353,1093],[388,1093],[388,1110],[353,1110]]},{"text":"（2）本篇一、二写在中共中央文化革命小组组长陈伯达、","box":[[415,1092],[1048,1092],[1048,1112],[415,1112]]},{"text":"副组长江青一九六七年一月十二日为送审这三个文件给林彪（在中共八届十一中","box":[[189,1139],[1049,1139],[1049,1162],[189,1162]]},{"text":"全会上当选为中央政治局常委，不久被称中央副主席）的报告（林彪当日即转报","box":[[190,1188],[1049,1189],[1049,1210],[190,1209]]},{"text":"毛泽东）上；本篇三写在陈伯达、江青同日为送审这三个文件给毛泽东的报告上。","box":[[190,1238],[1048,1238],[1048,1258],[190,1258]]},{"text":"（3）恩来，即周恩来，当时任国务院总理。","box":[[200,1286],[696,1286],[696,1309],[200,1309]]},{"text":"一九六七年一月十三日，中共中央、国务院关手在无产阶级文化大革命中加","box":[[239,1334],[1051,1334],[1051,1357],[239,1357]]},{"text":"强公安工作的若干规定","box":[[189,1383],[435,1383],[435,1406],[189,1406]]},{"text":"中发L67]19号","box":[[239,1432],[417,1432],[417,1455],[239,1455]]},{"text":"无产阶级文化大革命，是毛泽东思想挂师下的、无产阶级专政条件下的大民","box":[[240,1481],[1051,1481],[1051,1504],[240,1504]]},{"text":"主运动，它把广大群众的革命积极性调动起来了。形势大好。没有无产阶级专政","box":[[192,1531],[1045,1531],[1045,1551],[192,1551]]}],"dimensions":{"height":1755,"width":1241}}