{"ocr_results":[{"text":"258张春桥：1949及其后","box":[[129,89],[326,89],[326,104],[129,104]]},{"text":"第七章安亭事件259","box":[[1396,91],[1573,91],[1573,107],[1396,107]]},{"text":"我们绝对不能因为一部分的利益，因为有些人一时意气用事，而","box":[[235,152],[776,157],[776,180],[235,175]]},{"text":"33王力：《王力反思录》，第654页。","box":[[926,156],[1231,152],[1232,176],[926,180]]},{"text":"损害全国、全局的利益，损害我们伟大祖国的威望，即使是小小的损","box":[[198,187],[776,189],[776,208],[198,206]]},{"text":"34《建国以来毛泽东文稿》第六卷，中央文献出版社，1992年版，第398页。","box":[[926,188],[1561,187],[1561,209],[926,210]]},{"text":"害，也是不好的。","box":[[199,221],[336,221],[336,235],[199,235]]},{"text":"35王力：《王力反思录》，第654-655页。","box":[[926,220],[1268,216],[1268,239],[926,242]]},{"text":"事实上，你们这次的行动，不但影响本单位的生产，而且大大影","box":[[235,249],[775,253],[775,272],[235,268]]},{"text":"36上海文革史料整理编集小组：《上海文化大革命史话》，未刊稿，第174页。","box":[[925,250],[1568,249],[1568,272],[925,273]]},{"text":"响全国的交通。这是一个非常大的事件，希望你们现在立即改正，立","box":[[197,280],[775,283],[775,303],[197,299]]},{"text":"37耿金章，时为上海井冈山造纸厂工人。周宝林，时为上海市仪表局职工。","box":[[927,283],[1565,283],[1565,303],[927,303]]},{"text":"即回到上海，有问题就地解决。中央文化革命小组派张春桥同志即回","box":[[199,314],[774,316],[774,332],[199,330]]},{"text":"程琳，时为上海国棉三十一厂工人。","box":[[966,314],[1254,314],[1254,333],[966,333]]},{"text":"上海会见你们，你们有意见，可以和他当面商量。","box":[[199,345],[599,347],[599,363],[199,361]]},{"text":"38周国庭、陆云龙，均为上海铁路局江湾装卸机械广工人。","box":[[927,346],[1423,346],[1423,365],[927,365]]},{"text":"这是我们再三再三考虑才发出的电报。我们热烈希望你们接受我","box":[[235,374],[775,377],[775,396],[235,394]]},{"text":"39张春桥：《1966年11月16日接见上海工人革命造反司令部部分工人的讲","box":[[926,375],[1578,374],[1578,397],[926,398]]},{"text":"们的意见。向你们致无产阶级的最高敬礼。","box":[[198,406],[541,410],[541,426],[198,422]]},{"text":"话》，宋永毅主编：《中国文化大革命文库》（光盘），香港中文大学出版社，","box":[[966,410],[1564,411],[1564,427],[966,425]]},{"text":"1966年11月11日12时","box":[[596,437],[775,442],[774,461],[596,456]]},{"text":"2006年版。","box":[[966,439],[1052,439],[1052,458],[966,458]]},{"text":"陈伯达","box":[[722,473],[775,473],[775,490],[722,490]]},{"text":"40保皇派的本意是指清朝末代皇帝薄仪逊位后，张勋搞了个进京勤王的复牌","box":[[929,471],[1577,471],[1577,490],[929,490]]},{"text":"活动，原成戌变法领袖康有为拥立薄仪重登皇位，被称之为保皇派。文化","box":[[965,502],[1577,503],[1577,522],[965,521]]},{"text":"16","box":[[126,524],[166,524],[166,542],[126,542]]},{"text":"谢鹏飞和笔者的谈话，2014年2月23日。","box":[[161,524],[490,527],[490,543],[161,540]]},{"text":"大革命初期，从对国家主席刘少奇到基层的党政干部，群众持有“支持”与","box":[[966,534],[1575,536],[1575,553],[966,551]]},{"text":"17","box":[[124,555],[157,555],[157,573],[124,573]]},{"text":"同上。","box":[[162,556],[208,556],[208,573],[162,573]]},{"text":"“反对”两种截然不同的态度。1966年6月5日，《人民日报》刊发社论《做","box":[[966,564],[1578,565],[1578,585],[966,584]]},{"text":"18","box":[[124,587],[157,587],[157,605],[124,605]]},{"text":"张春桥：《1967年5月5日在济南军区干部会上的讲话》。","box":[[162,586],[618,588],[617,608],[162,605]]},{"text":"无产阶级革命派，还是做资产阶级保皇派》，随后“保皇派”一词被广泛引","box":[[967,598],[1575,598],[1575,614],[967,614]]},{"text":"19","box":[[124,618],[147,618],[147,637],[124,637]]},{"text":"王年一：《关于安亭事件的一些资料》，《党史资料研究》，2002年第二期。","box":[[162,617],[756,620],[755,639],[162,636]]},{"text":"用。毛泽东不赞成使用这一名称，在8月29日举行中央政治局常委扩大会","box":[[965,628],[1575,629],[1575,648],[965,647]]},{"text":"20","box":[[123,648],[158,648],[158,670],[123,670]]},{"text":"阿斗，三国时蜀汉后主刘禅的小名，以软弱无能著称。","box":[[163,648],[602,652],[602,670],[163,667]]},{"text":"议上说：“保皇派这个名称要取消。中央下的命令，人家怎么不保？”后来，","box":[[965,659],[1566,660],[1566,679],[965,678]]},{"text":"21","box":[[123,681],[157,681],[157,700],[123,700]]},{"text":"何秀文：《关于张春桥处理安亭事件的一些情况》","box":[[163,681],[564,684],[564,700],[163,697]]},{"text":"周恩来建议改保皇派为保守派。从人数来说，保守派占绝对优势，所以又","box":[[967,692],[1575,693],[1575,709],[967,708]]},{"text":"22","box":[[123,712],[161,712],[161,732],[123,732]]},{"text":"黄金海，时为上海国棉三十一厂车工。","box":[[163,712],[471,714],[470,730],[163,728]]},{"text":"被称多数派，造反派被称为少数派。在民间保守派被长时间的使用，保守","box":[[966,721],[1577,724],[1577,742],[966,739]]},{"text":"23","box":[[121,743],[161,743],[161,763],[121,763]]},{"text":"陈不显：《陈不显回忆录：在“一月风暴”的中心》，第94页。","box":[[160,743],[654,745],[654,763],[159,761]]},{"text":"派又常简称为“老保”。","box":[[968,755],[1154,755],[1154,771],[968,771]]},{"text":"24","box":[[124,776],[164,776],[164,792],[124,792]]},{"text":"张春桥：《1966年11月13日对上海工人造反总司令部赴京团代表的讲话》","box":[[160,776],[762,779],[762,795],[159,792]]},{"text":"41张春桥：《1966年11月21日接见上海工人造反司令部北上控告第一兵团的","box":[[930,786],[1575,787],[1575,803],[930,802]]},{"text":"宋永毅主编：《中国文化大革命文库》（光盘），香港中文大学出版社，2006","box":[[163,807],[772,810],[772,826],[163,823]]},{"text":"讲话》，宋永毅主编：《中国文化大革命文库》（光盘）。","box":[[965,816],[1408,817],[1408,836],[965,835]]},{"text":"年版。","box":[[163,838],[207,838],[207,856],[163,856]]},{"text":"42王洪文：《上海市委把炮口对准无产阶级司令部的罪行》。王洪文发言引用","box":[[927,848],[1578,849],[1578,868],[927,867]]},{"text":"25叶昌明，当时是上海合成纤维研究所化验工人，上海工总司发起人之一。","box":[[122,868],[751,873],[751,892],[122,887]]},{"text":"的资料来源为当时中共上海市委常委会的会议记录","box":[[968,882],[1385,882],[1385,898],[968,898]]},{"text":"26张宝林，时为上海建工局工人。","box":[[122,900],[414,901],[414,920],[122,919]]},{"text":"43曹获秋签字的《提卫毛泽东思想工人赤卫队上海总部八项要求》：","box":[[929,911],[1487,914],[1487,929],[929,927]]},{"text":"27上海文革史料编樂小组编：《上海文化大革命史话》，未刊打印稿，1994年，","box":[[122,932],[762,934],[762,953],[122,951]]},{"text":"一、高举毛泽东思想伟大红旗，坚决向华东局、上海市委所贯彻的资产","box":[[982,943],[1574,942],[1574,961],[982,962]]},{"text":"第174页。","box":[[161,962],[242,962],[242,982],[161,982]]},{"text":"阶级反动路线猛烈开火。","box":[[1018,976],[1212,976],[1212,991],[1018,991]]},{"text":"28","box":[[123,995],[164,995],[164,1013],[123,1013]]},{"text":"红鸥，原名侯美度，时为上海市市东中学高中女生，著名的造反英雄。","box":[[160,995],[731,999],[731,1015],[159,1011]]},{"text":"二、“捍卫毛泽东思想工人赤卫队上海总部”是群众性的革命组织，市委","box":[[982,1005],[1577,1006],[1577,1025],[982,1024]]},{"text":"29","box":[[122,1026],[147,1026],[147,1044],[122,1044]]},{"text":"李逊：《革命造反年代》，第343页。","box":[[161,1028],[446,1028],[446,1044],[161,1044]]},{"text":"必须为其抓革命，促生产和日常的工作提供一切必要的便利条件。","box":[[1018,1038],[1548,1039],[1548,1055],[1018,1053]]},{"text":"30","box":[[122,1058],[147,1058],[147,1076],[122,1076]]},{"text":"李逊：《革命造反年代》，第342页，注释107。","box":[[158,1057],[534,1059],[534,1079],[158,1076]]},{"text":"三、上海市委必须深刻地向全市革命群众公开检查所执行的资产阶级反","box":[[984,1069],[1575,1069],[1575,1085],[984,1085]]},{"text":"31","box":[[121,1089],[161,1089],[161,1109],[121,1109]]},{"text":"王力：《王力反思录》，香港北星出版社，2001年版，第653-654页。","box":[[160,1090],[711,1093],[711,1109],[159,1106]]},{"text":"动路线罪行。","box":[[1019,1101],[1117,1101],[1117,1117],[1019,1117]]},{"text":"32","box":[[123,1122],[162,1122],[162,1138],[123,1138]]},{"text":"《北航红旗五名战士与张春桥、戚本禹同志谈话纪要》，1966年11月8日，","box":[[156,1121],[762,1125],[762,1141],[156,1136]]},{"text":"四、上海市委所属各级执行资产阶级反动路线的当权派，也必须向各单","box":[[984,1133],[1597,1133],[1597,1149],[984,1149]]},{"text":"宋永毅主编《中国文化大革命文库》（光盘），香港中文大学出版社，2006","box":[[160,1151],[771,1154],[771,1173],[159,1171]]},{"text":"位的革命群众公开检查，并且在接到“捍卫毛泽东思想工人赤卫队上","box":[[1018,1163],[1575,1164],[1575,1180],[1018,1179]]},{"text":"年版。","box":[[159,1181],[208,1184],[207,1204],[158,1201]]},{"text":"海总部”会议通知时必须准时出席，听取革命群众的揭发批判。","box":[[1018,1195],[1527,1196],[1527,1212],[1018,1210]]}],"dimensions":{"height":1347,"width":1701}}