{"ocr_results":[{"text":"春节谈话纪要","box":[[770,97],[883,97],[883,118],[770,118]]},{"text":"月，不管衣食住行。章士钊不愿当袁世凯的官，让他当北大校长，","box":[[144,180],[879,180],[879,204],[144,204]]},{"text":"他跑到北大办报。黄炎老，你是立宪派的人？","box":[[141,226],[627,226],[627,249],[141,249]]},{"text":"1964年2月13日（春节），毛泽东邀请党内外负责人在人民大会堂召开","box":[[183,745],[882,746],[882,769],[183,768]]},{"text":"教育工作座谈会，提出学制要缩短，课程要精简，方法要改变。","box":[[141,785],[745,785],[745,805],[141,805]]},{"text":"黄炎培（以下简称黄）：我是革命派，不是立宪派，参加同盟","box":[[190,842],[880,842],[880,865],[190,865]]},{"text":"会的。","box":[[140,885],[203,885],[203,911],[140,911]]},{"text":"章：他是革命派的。","box":[[190,932],[402,932],[402,956],[190,956]]},{"text":"毛：陈叙老，你是研究系，章士钊二次革命，一九二五年当总","box":[[190,978],[880,978],[880,1001],[190,1001]]},{"text":"长，现在你们都跟我们一起了，在新中国参加社会主义建设。我们","box":[[142,1022],[883,1022],[883,1046],[142,1046]]},{"text":"今年的工作想法做得更好一些，不但是中央希望，也是你们的希","box":[[143,1067],[881,1067],[881,1091],[143,1091]]},{"text":"望。许德珩，你是工业部的？","box":[[141,1113],[453,1113],[453,1136],[141,1136]]},{"text":"：他的部大有希望。","box":[[189,1156],[478,1155],[478,1182],[190,1183]]},{"text":"毛：黄老，你的家族像各党各派，民盟、民进、共青团，你的","box":[[191,1202],[881,1202],[881,1226],[191,1226]]},{"text":"儿子黄万里写的“贺新郎”词写得好，我欣赏。九三学社中一人诗","box":[[142,1248],[882,1248],[882,1272],[142,1272]]},{"text":"243","box":[[846,1325],[890,1325],[890,1353],[846,1353]]}],"dimensions":{"height":1418,"width":1005}}