{"ocr_results":[{"text":"四、分配","box":[[359,120],[459,120],[459,141],[359,141]]},{"text":"351","box":[[660,119],[687,119],[687,140],[660,140]]},{"text":"生产资料重新分散于个人的手中。这是给自已的前提-记耳光，","box":[[109,174],[700,174],[700,190],[109,190]]},{"text":"是达到了纯粹荒唐的地步。","box":[[108,209],[349,209],[349,226],[108,226]]},{"text":"活的劳动，即能动的劳动力，应当和劳动产品相交换。于是它","box":[[148,242],[704,241],[704,261],[148,262]]},{"text":"和与之交换的产品一样，也是商品。于是这种劳动力的价值就决","box":[[108,277],[704,277],[704,297],[108,297]]},{"text":"不会根据它的产品来决定，而是根据它里面所体现的社会劳动，即","box":[[108,313],[704,312],[704,332],[108,333]]},{"text":"根据目前的工资规律来决定。","box":[[109,350],[370,350],[370,367],[109,367]]},{"text":"但是，这正好是不应该有的情形。流通的劳动，即劳动力，是","box":[[151,385],[703,385],[703,402],[151,402]]},{"text":"应当可以和它的全部产品相交换的。这就是说，它应当不和它的","box":[[109,419],[703,419],[703,436],[109,436]]},{"text":"价值相交换，而和它的使用价值相交换；价值规律应当适用于其他","box":[[107,453],[704,452],[704,472],[107,473]]},{"text":"一切商品，但是对于劳动力，它是应该被废除的。隐藏在“劳动价","box":[[107,488],[704,487],[704,507],[107,508]]},{"text":"值”背后的，正是这种自己消灭自己的混乱观念。","box":[[108,524],[542,524],[542,541],[108,541]]},{"text":"“劳动和劳动根据平等估价的原则相交换”，这句话如果有意","box":[[149,560],[703,559],[703,576],[149,577]]},{"text":"义的话，那末就是说，等量社会劳动的产品可以相互交换，就是说，","box":[[109,595],[699,595],[699,612],[109,612]]},{"text":"价值规律正是商品生产的基本规律，从而也就是商品生产的最高","box":[[109,631],[702,631],[702,647],[109,647]]},{"text":"形式即资本主义生产的基本规律。在目前的社会中，它以经济规","box":[[109,665],[702,665],[702,682],[109,682]]},{"text":"律在私人生产者的社会里唯-一能为自已开辟道路的那种方式，即","box":[[107,700],[703,699],[703,718],[107,719]]},{"text":"作为存在于事物和关系中的、不以生产者的愿望或努力为转移的、","box":[[108,736],[701,736],[701,753],[108,753]]},{"text":"盲目地起作用的自然规律来为自己开辟道路。杜林先生把这一规","box":[[107,770],[703,769],[703,788],[107,789]]},{"text":"律提升为他的经济公社的基本规律，并且要求公社完全自觉地实","box":[[108,806],[702,806],[702,823],[108,823]]},{"text":"施这个规律，这样，他就使现存社会的基本规律成为他的幻想社会","box":[[107,841],[702,840],[702,858],[107,859]]},{"text":"的基本规律。他要现存的社会，但不要它的弊病。他和蒲鲁东完","box":[[107,876],[703,875],[703,892],[107,893]]},{"text":"全在同一个基地上进行活动。象蒲鲁东一样，他想消除由于商品","box":[[106,911],[703,910],[703,930],[106,931]]},{"text":"生产向资本主义生产的发展而产生的弊病，办法是利用商品生产","box":[[105,945],[703,944],[703,964],[105,965]]},{"text":"的基本规律去反对这些弊病，而这些弊病正是由这一规律的作用","box":[[106,981],[703,980],[703,1000],[106,1001]]},{"text":"产生的。象蒲鲁东-样，他想以幻想的结果来消灭价值规律的现","box":[[106,1017],[703,1017],[703,1034],[106,1034]]},{"text":"实结果。","box":[[105,1050],[178,1050],[178,1071],[105,1071]]}],"dimensions":{"height":1200,"width":816}}