{"ocr_results":[{"text":"第七章贵州“文革”购及“贵州事件”11","box":[[719,26],[953,43],[952,63],[717,45]]},{"text":"L","box":[[489,49],[511,49],[511,63],[489,63]]},{"text":"m","box":[[579,48],[602,46],[603,60],[581,62]]},{"text":"iL贺州风云","box":[[162,73],[245,62],[247,77],[164,88]]},{"text":"还新下49万多人，全县死第户3001户，孤儿近5000人，外出逃范","box":[[150,114],[523,93],[525,123],[151,143]]},{"text":"（六）贵州魂亡灵有《墓碑》","box":[[672,110],[867,114],[867,131],[672,127]]},{"text":"5000多人，全县出现了人吃人、杀人而食、易子而食的修刷，县威时","box":[[149,133],[522,114],[524,143],[151,162]]},{"text":"见联卖以人内充当的牛肉，吃死去的人就更多了。后来“调源事件”","box":[[150,154],[522,135],[524,162],[151,180]]},{"text":"针对“贵州事件”，贵工师生经过几个月的努力，做了大量调研工","box":[[594,149],[964,154],[963,181],[594,176]]},{"text":"（脚系，的盖于提开，省、地组织了晓大的工作组到这里夺权，“整风","box":[[148,173],[522,156],[523,182],[150,200]]},{"text":"作，采访了数十位当事人，积累了大量原始资料，记录了人额、黑暗","box":[[568,171],[964,171],[964,202],[568,202]]},{"text":"整社”，一个运动接着一个运动在这里开展，都是以“左“反“左”，反","box":[[149,192],[521,177],[522,203],[150,218]]},{"text":"和罪恶，由张再兴编撰，昆明陈安民先生印刷，形成了一本包括（遵","box":[[568,191],[964,192],[963,222],[568,220]]},{"text":"“左”的结果是基层干部遗殊，被处理的基层干部，包括杀、关、管、","box":[[149,212],[521,198],[522,222],[149,236]]},{"text":"义事件“请谈录》在内的《贵州事件调查资料集（上）26万字，这是","box":[[569,211],[963,213],[963,240],[569,239]]},{"text":"集训、判刑和开除公职等，占60%以上，最为突出的是湘潭县委书","box":[[148,231],[521,219],[521,243],[149,255]]},{"text":"凝固的记忆，虽尚未正式出版，但也可称之为贵州机魂亡灵的（基碑》。","box":[[570,234],[957,234],[957,259],[570,259]]},{"text":"记王师臣判利劳改，县长兼绥阳区区长容镜被处决。容镜后来被平","box":[[148,251],[519,240],[519,262],[149,273]]},{"text":"《基碑》，这是毕业于清华大学理工专业的新华社高级记者、著","box":[[596,255],[960,257],[960,277],[596,275]]},{"text":"反。","box":[[150,275],[167,275],[167,290],[150,290]]},{"text":"名学者杨继绳写的一本书，分上下卷共110万字，其副题是（中国","box":[[570,276],[960,275],[960,297],[570,298]]},{"text":"安在淄潭县的调查工作有遵义地委办公室一位副主任和地区","box":[[171,290],[518,284],[519,303],[172,310]]},{"text":"六十年代大机荒纪实》。“大跃进”年代的大荒，在全国是普遍性","box":[[570,297],[958,297],[958,317],[570,317]]},{"text":"公安处二位工作人员配合进行。随后爱又赶赴毕节专区，专署公安","box":[[148,309],[518,305],[518,325],[148,328]]},{"text":"的，四川、安徽、贵州、河南、山东、甘肃、青海等省都是重灾区。湖北","box":[[569,318],[958,317],[958,336],[569,337]]},{"text":"处长朱广臣接待了他，并派秘书科和治安科二位同志陪同晏到金","box":[[147,330],[517,327],[517,344],[147,347]]},{"text":"省潘水农村出身的杨继绳，其父亲就是在“大跃进”大荒时饿死","box":[[570,340],[956,339],[956,354],[570,355]]},{"text":"沙县调查：晏在安洛公社安洛大队了解到，该大队有一个生产队29","box":[[147,351],[516,349],[516,364],[147,366]]},{"text":"的。杨继绳从上世纪90年代初开始，利用到全国各地采访的机会","box":[[572,361],[954,361],[954,373],[572,373]]},{"text":"户人家，共152人，除一人在贵阳钢铁厂当工人，一人在习水县号","box":[[149,371],[514,371],[514,383],[149,383]]},{"text":"水造纸厂当工人外，其余150人全部饿死。后来到1961年底1962","box":[[147,391],[515,391],[515,404],[147,403]]},{"text":"从天西北到大西南，从华北到华东，从东北到华南，查阅了十几个","box":[[572,383],[954,383],[954,393],[572,393]]},{"text":"年初，金沙县饿死人的盖子揭开之后，那三年全县饿死了8万多","box":[[145,409],[516,411],[516,426],[145,424]]},{"text":"省的资料，访谈了上百位当事人，收集了上千万字的资料，写出了","box":[[570,400],[954,399],[954,414],[570,414]]},{"text":"人，县委书记赵广玉自己讲饿死了4.7万人。后赵广玉被速捕法办，","box":[[145,428],[513,432],[513,447],[145,443]]},{"text":"这本在香港出版的书，书中确认“大跃进”大荒年代全国饿死","box":[[570,420],[955,419],[955,434],[570,435]]},{"text":"判处徒刑8年，投人劳改农场改造，后平反，被安排到铜仁地区工","box":[[144,447],[516,452],[515,469],[144,464]]},{"text":"3600多万人，他把他的这本书当作全国这几千万机魂亡灵的一座","box":[[568,438],[956,437],[956,457],[568,457]]},{"text":"作：县长王国民后因骑马挥死，未追究其责任。","box":[[145,467],[388,473],[387,486],[144,479]]},{"text":"落碑，愿他们能因此得到安感。","box":[[570,459],[751,463],[750,478],[570,473]]},{"text":"1960年12月至1961年5月，委随公安厅办公室主任刘世杰","box":[[167,485],[516,492],[515,512],[167,505]]},{"text":"杨继绳2002年12月也到贵州省档案馆查过贵州“大跃进”大","box":[[592,478],[954,476],[954,496],[593,498]]},{"text":"到六盘水地区的水城县参加整风整社工作，经过工作队搜集了解，","box":[[142,503],[514,513],[513,533],[142,523]]},{"text":"机荒资料，并开列出一张30份资料的目录清单，拟带出但未获准","box":[[566,495],[956,493],[956,518],[566,519]]},{"text":"1959年至1961年5月，全水城县饿死8万多人。后来县委书记刘","box":[[141,521],[516,531],[516,554],[140,545]]},{"text":"许，他把这张单子也列人了《基碑）书中。此书以《黑色的贵州》为题","box":[[565,514],[955,512],[955,538],[565,541]]},{"text":"福臣被速捕法办，判刑劳改。[附录8","box":[[143,542],[338,552],[337,567],[142,556]]},{"text":"介绍了贵州。","box":[[570,537],[640,542],[639,555],[569,550]]},{"text":"早在1991年，另一名清华大学理工科毕业生丁齐在香港出版","box":[[590,555],[953,550],[954,577],[590,581]]},{"text":"了《人锅：大跃进和大机竞》。这是忠实记录那段历史的第一本中文","box":[[565,571],[953,569],[954,599],[565,601]]},{"text":"著现在美国明尼苏达若曼学院教援的于打的盖论文（美进","box":[[562,589],[953,586],[954,620],[563,622]]},{"text":"大机能期向非正常死亡的下限》认定其下限为3300万人","box":[[562,607],[910,610],[910,642],[562,639]]},{"text":"08年初那场银死人的修刷已经过去，生命方似子无照的中","box":[[587,630],[952,623],[952,657],[587,664]]},{"text":"加，反是145810人，而不是12.5万人。","box":[[144,686],[312,702],[310,714],[143,698]]},{"text":"94","box":[[150,717],[165,717],[165,730],[150,730]]},{"text":"95","box":[[924,720],[939,720],[939,733],[924,733]]}],"dimensions":{"height":757,"width":1071}}