{"ocr_results":[{"text":"价格由生产费用决定这一点，不应当了解成像济学家例所","box":[[104,98],[658,98],[658,116],[104,116]]},{"text":"了解的那种意思。經济学家何，商品的平均价格等于生产费用","box":[[64,134],[655,134],[655,152],[64,152]]},{"text":"在他何看来，这是一个规律。他們把价格的上涨被价格的下降所","box":[[61,171],[658,171],[658,189],[61,189]]},{"text":"抵销，而下降则被上涨所抵销这种无政府状态的变动看作偶然现","box":[[60,207],[658,207],[658,225],[60,226]]},{"text":"象。那么，同样也可以（另一些經济学家就正是这样做的）把价格","box":[[60,245],[657,244],[657,262],[60,262]]},{"text":"的波动看作规律，而把价格由生产费用决定这一点看作偶然现象。","box":[[60,280],[655,280],[655,298],[60,298]]},{"text":"可是实际上，只有在这种波动的进程中，价格才是由生产赛用决定","box":[[61,317],[658,318],[658,336],[61,335]]},{"text":"的；我們翻加分析时就可以看出，这种波动起着极可怕的破坏作","box":[[60,354],[658,353],[658,372],[60,373]]},{"text":"用，并像地震一样震瓷产阶社会的基础。这种无秩序状态的","box":[[61,391],[658,391],[658,409],[61,409]]},{"text":"总运动就是它的秩序。在这种产业无政府状态的进程中，在这种","box":[[61,428],[658,428],[658,446],[61,446]]},{"text":"循环运轉中，竞争可以證是拿一个极端去抵銷另一个极端。","box":[[61,465],[593,465],[593,483],[61,483]]},{"text":"由此可見，商品价格是由生产费用这样来决定的：某些时期，","box":[[106,503],[654,503],[654,519],[106,519]]},{"text":"某种商品的价格超过它的生产费用，另一些时期，酸商品的价格却","box":[[61,538],[658,538],[658,556],[61,556]]},{"text":"下跌到它的生产费用以下，而抵销以前超过的时期，反之亦然。当","box":[[64,576],[657,576],[657,592],[64,592]]},{"text":"然，这不是就个别产业的产品来的，而只是就整个产业部門来證","box":[[61,612],[659,612],[659,630],[61,630]]},{"text":"的。所以，这同样也不是就个别产业家来的，而只是就整个产业","box":[[47,648],[657,648],[657,666],[47,666]]},{"text":"家阶额来酰的。","box":[[61,686],[193,686],[193,702],[61,702]]},{"text":"价格由生产费用决定，就等于价格由生产商品所必需的劳","box":[[104,721],[657,721],[657,740],[104,739]]},{"text":"动时周决定，因为构成生产费用的是：（1）原料和劳动工具①，即","box":[[61,759],[658,759],[658,777],[61,777]]},{"text":"产业产品，它调的生产耗费了一定数量的工作日，因而也就是代表","box":[[61,794],[657,794],[657,812],[61,812]]},{"text":"一定数量的劳动时間；（2）直接劳动，它也是以时間計量的。","box":[[61,831],[603,832],[603,850],[61,850]]},{"text":"一般节商品价格的那些最一般的规律，当然也节工，助","box":[[105,870],[657,870],[657,885],[105,885]]},{"text":"鹏节劳动价格。","box":[[61,906],[195,906],[195,924],[61,924]]},{"text":"劳动报酬忽而提高，忽而降低，是依供求关系为轉移的，依购","box":[[104,941],[658,943],[658,961],[103,959]]},{"text":"①在1891年的版本中，“劳动工具*改为“劳动工具捐耗部分*。一者注","box":[[94,1019],[629,1019],[629,1034],[94,1034]]},{"text":"21","box":[[609,1058],[641,1058],[641,1076],[609,1076]]}],"dimensions":{"height":1168,"width":785}}