{"books":[{"id":"whb","name":"文汇报","internal":false,"official":false,"type":"db","author":"","files":[],"article":{"title":"人民出版社等出版有关宪法的书籍","authors":[],"dates":[{"year":1954,"month":6,"day":29}],"is_range_date":false,"parts":[{"type":"paragraph","text":"【新华社北京二十八日电】　为了供应全国人民在讨论宪法草案中的需要，人民出版社、新华书店正陆续出版、发行有关宪法的书籍。人民出版社已先后出版中华人民共和国宪法草案单行本一百八十五万册，分批交由新华书店发行，并将宪法草案纸型发给各地印造，以便普遍供应。人民出版社最近还出版了“宪法·苏联宪法”(苏联大百科全书选译)，即将出版的初版书有“斯大林宪法制定、批准与发展的历史”。新华书店也已预备了各种参考书作重点发行。这些参考书包括毛泽东同志著的“新民主主义论”和“论人民民主专政”，人民出版社等出版的“宪法的概念与本质”、“人民民主国家宪法汇编”、“资产阶级民主的剖视”等。"}],"comments":[],"origin":"新华社","comment_pivots":[],"description":"","page_start":1,"page_end":1,"alias":""},"tags":[{"type":"文稿类型","name":"文章"}]}]}