{"ocr_results":[{"text":"第944页，共1890页","box":[[829,53],[1088,53],[1088,76],[829,76]]},{"text":"三十九、人民公社社员的家庭副业，是社会主义经济的必要的补充部分。","box":[[290,164],[1049,164],[1049,186],[290,186]]},{"text":"它附属于集体所有制经济和全民所有制经济，是它们的助手。在积极办好集体经","box":[[191,214],[1050,214],[1050,234],[191,234]]},{"text":"济，不妨碍集体经济的发展，保证集体经济占绝对优势的条件下，人民公社应该","box":[[190,264],[1050,264],[1050,284],[190,284]]},{"text":"允许和鼓励社员利用剩余时间和假日，发展家庭副业，增加社会产品，增加社员","box":[[191,311],[1048,312],[1048,333],[191,332]]},{"text":"收入，活跃农村市场。","box":[[191,360],[475,360],[475,380],[191,380]]},{"text":"四十、人民公社社员可以经营以下的家庭副业生产：","box":[[486,361],[1044,361],[1044,381],[486,381]]},{"text":"（一)耕种由集体分配的自留地。自留地一般占生产队耕地面积的百分之五到七，","box":[[203,410],[1046,410],[1046,430],[203,430]]},{"text":"归社员家庭使用，长期不变。在有柴山和荒坡的地方，还可以根据群众需要和原","box":[[192,459],[1050,459],[1050,479],[192,479]]},{"text":"有习惯，分配给社员适当数量的自留山，由社员经营。自留山划定以后，也长期","box":[[190,508],[1050,508],[1050,527],[190,527]]},{"text":"不变。","box":[[188,553],[322,553],[322,577],[188,577]]},{"text":"（二）饲养猪、羊、兔、鸡、鸭、鹅等家畜家禽，也可以饲养母猪和","box":[[316,555],[1049,554],[1049,575],[316,576]]},{"text":"大牲畜，为了发展养猪业，以便给集体经济提供较多的肥料，在有需要、有条件","box":[[189,603],[1050,603],[1050,626],[189,626]]},{"text":"的地方，生产队可以按照本队土地的情况，经过社员讨论，拨给社员适当数量的","box":[[189,651],[1051,652],[1051,675],[189,674]]},{"text":"饲料地。这种饲料地，应该尽可能利用现有的闲散地或者小片荒地。","box":[[191,702],[926,702],[926,722],[191,722]]},{"text":"（二）","box":[[999,704],[1048,704],[1048,723],[999,723]]},{"text":"经过生产队社员大会讨论和公社或者生产大队批准，在统一规划下，可以开垦零","box":[[188,749],[1051,750],[1051,773],[188,772]]},{"text":"星荒地。开垦的荒地一般可以相当于自留地的数量，在人少地多的地方可以少一","box":[[191,800],[1049,800],[1049,820],[191,820]]},{"text":"点，在人多地少的地方也可以略多一点。","box":[[190,848],[668,849],[668,870],[190,869]]},{"text":"开荒绝对不许破坏水土保持，破坏","box":[[680,849],[1050,848],[1050,869],[680,870]]},{"text":"山林，破坏草原，破坏水利工程，妨碍交通。","box":[[192,897],[733,897],[733,917],[192,917]]},{"text":"社员的自留地、饲料地和开荒","box":[[721,896],[1050,896],[1050,919],[721,919]]},{"text":"地合在一起的数量，根据各个地方土地的不同情况，有多有少，在一般情况下，","box":[[189,944],[1045,944],[1045,967],[189,967]]},{"text":"可以占生产队耕地面积的百分之五到百分之十，最多不能超过百分之十五。","box":[[192,995],[996,995],[996,1015],[192,1015]]},{"text":"（四）进行编织、缝纫、刺绣等家庭手工业生产。","box":[[203,1044],[726,1044],[726,1064],[203,1064]]},{"text":"（五）从事采集、渔猎、","box":[[798,1044],[1046,1044],[1046,1064],[798,1064]]},{"text":"养蚕、养蜂等副业生产。","box":[[190,1092],[502,1091],[502,1112],[190,1113]]},{"text":"（六）经营由集体分配的自留果树和竹木。在屋前","box":[[519,1093],[1049,1093],[1049,1113],[519,1113]]},{"text":"屋后或者在生产队指定的其他地方种植果树、桑树和竹木。这些东西永远归社员","box":[[191,1141],[1048,1141],[1048,1161],[191,1161]]},{"text":"所有。","box":[[189,1188],[312,1188],[312,1212],[189,1212]]},{"text":"社员经营家庭副业，使用集体所有的牲畜和工具等生产资料的时候，","box":[[310,1190],[1043,1190],[1043,1210],[310,1210]]},{"text":"都要付给集体以适当的代价。","box":[[192,1237],[559,1237],[559,1257],[192,1257]]},{"text":"四十一、社员家庭副业的产品和收入，都归社","box":[[556,1237],[1051,1237],[1051,1260],[556,1260]]},{"text":"员所有，都归社员支配。在完成同国家订立的定购合同以后，除了国家有特殊限","box":[[192,1287],[1049,1287],[1049,1307],[192,1307]]},{"text":"制的以外，其余的产品，都可以拿到集市上出售。","box":[[191,1334],[763,1335],[763,1356],[191,1355]]},{"text":"社员的自留地和开荒地生","box":[[779,1334],[1050,1335],[1050,1356],[779,1355]]},{"text":"产的农产品，不算在集体分配的产量和集体分配的口粮以内，国家不征收农业税，","box":[[190,1384],[1046,1384],[1046,1404],[190,1404]]},{"text":"不计统购。","box":[[190,1433],[350,1433],[350,1454],[190,1454]]},{"text":"四十二、人民公社各级管理委员会，对于社员经营家庭副业，应","box":[[358,1434],[1050,1434],[1050,1454],[358,1454]]},{"text":"该给以必要的指导和帮助，不要乱加十涉。同时，又要教育社员兼顾国家、集体","box":[[192,1483],[1051,1483],[1051,1503],[192,1503]]},{"text":"和个人的利益，积极参加和关心集体生产，不损害公共利益，不弃农经商，不投","box":[[189,1529],[1051,1530],[1051,1553],[189,1552]]}],"dimensions":{"height":1755,"width":1241}}