{"ocr_results":[{"text":"第46页，共1862页","box":[[842,53],[1087,53],[1087,77],[842,77]]},{"text":"《吴德口述：十年风雨纪事一一我在北京工作的一些经历》","box":[[277,237],[897,237],[897,261],[277,261]]},{"text":"作者：吴德朱元石","box":[[314,302],[536,302],[536,329],[314,329]]},{"text":"1973年8月，党的十大召开。在这次党代会上，我再次当选为中央委员，","box":[[265,368],[1046,367],[1046,391],[266,392]]},{"text":"并进入了中央政治局。由于毛主席的赞同，党内老一辈的无产阶级革命家、军事","box":[[192,434],[1050,434],[1050,457],[192,457]]},{"text":"家，如朱德、董必武、刘伯承等同志在这次党代会上当选为中央政治局委员。同","box":[[191,499],[1049,499],[1049,523],[191,523]]},{"text":"时，党的十大也使江青集团的很多骨干分子当选为中央委员，使江青、张春桥、","box":[[191,562],[1042,562],[1042,585],[191,585]]},{"text":"姚文元、王洪文进入了中央政治局，并且使王洪文当选为中央副主席。","box":[[191,629],[942,629],[942,652],[191,652]]},{"text":"毛主","box":[[1004,629],[1050,629],[1050,652],[1004,652]]},{"text":"席对政治局的同志，尤其是对王洪文、张春桥、江青、姚文元当时是寄予了希望","box":[[191,693],[1047,693],[1047,716],[191,716]]},{"text":"的。我记得十大后不久，毛主席在游泳池住处找我们谈话，曾经向政治局提出扶","box":[[191,759],[1050,759],[1050,782],[191,782]]},{"text":"助他们。毛主席指着窗外菜地里的一些碧绿的蔬菜比喻说：就像培植它们的生长","box":[[191,824],[1049,824],[1049,847],[191,847]]},{"text":"一样。","box":[[190,888],[304,888],[304,913],[190,913]]},{"text":"江青集团的政治地位虽然由于十大的召开得到了巩固，但他们夺取党","box":[[308,888],[1049,888],[1049,911],[308,911]]},{"text":"和国家最高权力的野心和活动也逐渐暴露了，毛主席发现、批评并提出解决江青","box":[[191,953],[1049,953],[1049,976],[191,976]]},{"text":"宗派集团的问题。","box":[[191,1018],[373,1018],[373,1039],[191,1039]]},{"text":"1975年5月3日，毛主席召开中央政治局会议，批评江","box":[[440,1017],[1040,1017],[1040,1040],[440,1040]]},{"text":"青等人反经验主义、搞宗派活动、在“批林批孔”运动中搞“三箭齐发”，并且","box":[[190,1082],[1049,1083],[1049,1107],[190,1106]]},{"text":"说明他们是“四人帮”。毛主席说：“不要搞四人帮，你们不要搞了，为什么照","box":[[193,1149],[1049,1149],[1049,1172],[193,1172]]},{"text":"样搞呀?为什么不和二百多个中央委员搞团结，搞少数人不好，历来不好。”“我","box":[[189,1210],[1052,1212],[1052,1238],[189,1236]]},{"text":"看批经验主义的人，自己就是经验主义，马列主义不多。”“我看江青就是一个","box":[[189,1275],[1049,1276],[1049,1303],[189,1302]]},{"text":"小小的经验主义者。”毛主席还说：“我看问题不大，不要小题大做，但有问题","box":[[194,1343],[1049,1343],[1049,1367],[194,1367]]},{"text":"要讲明白，上半年解决不了，下半年解决；今年解决不了，明年解决；明年解决","box":[[191,1408],[1049,1408],[1049,1432],[191,1432]]},{"text":"不了，后年解决。”这一次，毛主席虽然说问题不大，但却作出了一个重要的指","box":[[192,1473],[1048,1473],[1048,1497],[192,1497]]},{"text":"示，即不论时间多久，也要解决这个问题。正因为如此，中央政治局在5月3","box":[[189,1537],[1029,1536],[1029,1563],[189,1564]]}],"dimensions":{"height":1755,"width":1241}}