{"ocr_results":[{"text":"林立果将林彪给黄永胜的亲笔信交给王飞，要王飞和黄永胜取得","box":[[198,236],[1449,238],[1449,275],[198,273]]},{"text":"联系。林彪亲笔信全文是：“永胜同志：很惦念你，望任何时候","box":[[196,311],[1450,309],[1450,351],[196,353]]},{"text":"都要乐观保护身体有事时可与王飞同志面洽。”这是反革命的","box":[[201,389],[1451,389],[1451,426],[201,426]]},{"text":"，“接头信”，实际上是林彪的又一个手令。不知何故，此信始终","box":[[190,460],[1448,461],[1448,501],[190,500]]},{"text":"未交给黄永胜。","box":[[199,537],[483,537],[483,575],[199,575]]},{"text":"林立果、周宇驰，于新野等人要谋害的是毛泽东主席，面对","box":[[286,614],[1450,613],[1450,651],[286,652]]},{"text":"的却是整个人民。他们既要搞反革命武装政变，又不能公然进行，","box":[[200,688],[1444,689],[1444,726],[200,725]]},{"text":"既要一些人供他们驱使，又不能让这些人了解底细。这是无法解","box":[[200,764],[1450,764],[1450,802],[200,802]]},{"text":"脱的矛盾。尽管他们阴险、毒辣，狡诈，但是到了9月11日还是","box":[[200,839],[1452,841],[1452,878],[200,876]]},{"text":"没有商定一个谋害毛泽东的办法。事到临头，谁也不敢干。9月","box":[[197,916],[1447,915],[1447,952],[197,953]]},{"text":"11日，叶群一再催促动手；但是就在当夜，王维国从上海打电话","box":[[196,990],[1450,991],[1450,1028],[196,1027]]},{"text":"向他们密报：毛泽东已经离开上海北上了！","box":[[198,1066],[1023,1067],[1023,1105],[198,1104]]},{"text":"（3）震惊中外的“九·一三”事件","box":[[476,1191],[1182,1192],[1182,1233],[476,1232]]},{"text":"8月31日，毛泽东乘坐列车到了南昌。他听取了江西省革委","box":[[298,1297],[1453,1297],[1453,1337],[298,1337]]},{"text":"会一负责人关于周宇驰等人在江西进行了一些反常活动的报告。","box":[[200,1375],[1429,1371],[1429,1408],[200,1412]]},{"text":"9月3日深夜，毛泽东到达杭州。他在年轻的服务人员中了解到","box":[[205,1451],[1452,1447],[1452,1484],[205,1488]]},{"text":"林立果一伙活动的一些情况，提高了警惕性，机警地改变了活动","box":[[199,1525],[1454,1525],[1454,1562],[199,1562]]},{"text":"规律。南昌报告的是一般情况，毛泽东真正有所觉察是在杭州。","box":[[196,1595],[1428,1597],[1428,1638],[196,1636]]},{"text":"他在杭州同当地负责人谈话时，问了陈励耘：“你同吴法宪的关","box":[[199,1671],[1454,1673],[1454,1714],[199,1712]]},{"text":"系如何？吴法宪在庐山找了几个人，有你陈励耘，有上海的王维","box":[[200,1747],[1456,1747],[1456,1787],[200,1787]]},{"text":"国，还有海军的什么人。你们都干了些什么？”陈励耘狼狈不堪，","box":[[199,1820],[1451,1820],[1451,1864],[199,1864]]},{"text":"答非所问。9月8日深夜，毛泽东突然密令立即把他乘坐的专列","box":[[199,1896],[1456,1895],[1456,1939],[199,1940]]},{"text":"从筑桥机场的专线上转移到绍兴，以迷惑敌人。9月10日下午3","box":[[201,1969],[1449,1968],[1449,2015],[201,2016]]},{"text":"时，毛泽东突然立即离开杭州，并且不要陈励耘送行。9月10日","box":[[196,2045],[1453,2042],[1453,2091],[196,2094]]},{"text":"下午6时，毛泽东到达上海。他不下专列，在车上接见了当地党","box":[[196,2120],[1458,2122],[1458,2169],[196,2167]]},{"text":"·426.","box":[[252,2217],[388,2217],[388,2252],[252,2252]]}],"dimensions":{"height":2411,"width":1659}}