{"ocr_results":[{"text":"的国家只能是无产阶级的革命专政","box":[[181,237],[805,236],[806,267],[181,268]]},{"text":"马克思：《哥达纲领批判》（一八七五年四","box":[[480,306],[1043,305],[1043,329],[480,330]]},{"text":"月一五月初），《马克思恩格斯选集》第3","box":[[514,355],[1038,351],[1038,375],[514,378]]},{"text":"卷第21页。","box":[[511,401],[665,401],[665,429],[511,429]]},{"text":"这种社会主义就是宣布不断革命，就是无产","box":[[263,526],[1047,523],[1047,559],[263,562]]},{"text":"阶级的阶级专政，这种专政是达到消灭一切阶级","box":[[180,597],[1045,596],[1045,629],[180,630]]},{"text":"差别，达到消灭这些差别所由产生的一切生产关","box":[[177,666],[1047,664],[1047,699],[177,701]]},{"text":"系，达到消灭和这些生产关系相适应的一切社会","box":[[181,739],[1045,734],[1045,765],[181,770]]},{"text":"关系，达到改变由这些社会关系产生出来的一切","box":[[181,808],[1046,804],[1046,837],[181,840]]},{"text":"观念的必然的过渡阶段","box":[[181,875],[603,874],[604,907],[181,908]]},{"text":"马克思：《一八四八年至一八五（）年的法兰","box":[[486,944],[1049,944],[1049,967],[486,967]]},{"text":"西阶级斗争》（一八五〇年一月一十一月","box":[[518,992],[1046,992],[1046,1015],[518,1015]]},{"text":"一日），《马克思恩格斯选集》第1卷第","box":[[518,1040],[1049,1040],[1049,1063],[518,1063]]},{"text":"479-480页。","box":[[517,1085],[690,1085],[690,1113],[517,1113]]},{"text":"通过把一切劳动资料转交给生产者的办法消","box":[[270,1217],[1049,1217],[1049,1249],[270,1249]]},{"text":"灭现存的压道条件，从而道使每一个体力适合于","box":[[185,1286],[1052,1284],[1052,1319],[186,1321]]},{"text":"工作的人为保证自己的生存而工作，这样，我们","box":[[186,1356],[1053,1354],[1053,1385],[186,1387]]},{"text":"就会消灭阶级统治和阶级压道的唯一的基础。但","box":[[185,1426],[1052,1424],[1052,1456],[186,1459]]},{"text":"是，必须先实行无产阶级专政，才可能实现这种变","box":[[184,1496],[1052,1491],[1052,1526],[184,1531]]},{"text":"革，而无产阶级专政的首要条件就是无产阶级的","box":[[185,1565],[1051,1561],[1051,1596],[186,1600]]},{"text":"5","box":[[1009,1634],[1027,1634],[1027,1662],[1009,1662]]}],"dimensions":{"height":1755,"width":1240}}