{"ocr_results":[{"text":"第626页，共5150页","box":[[830,55],[1086,55],[1086,75],[830,75]]},{"text":"薄：我们工作组作的是对的，工作组一进村就支持左派，站在左派一边，反","box":[[241,166],[1049,166],[1049,186],[241,186]]},{"text":"对保皇派，反对牛鬼蛇神，工作组作的是对的，当然工作组刚进校情况不熟，他","box":[[190,215],[1049,215],[1049,235],[190,235]]},{"text":"们都是从上海东北来的，一进校他们就听毛主席的话按毛主席教导去作，起来调","box":[[192,264],[1049,264],[1049,284],[192,284]]},{"text":"查研究，不能下车伊始就哇喇哇喇，制大富就抓往这一点说工作组来了以后不马","box":[[190,313],[1049,313],[1049,333],[190,333]]},{"text":"上斗他们，前大富之流所说要斗保皇派，实际上要斗我们所说的真正左派，工作","box":[[189,357],[1051,359],[1051,383],[189,380]]},{"text":"组没答应他们的要求，说要调查研究，调查清楚了才能斗。脚大富不允许，我说","box":[[190,410],[1051,410],[1051,429],[190,429]]},{"text":"这不对，他就说一切牛鬼蛇神都抓出来了，当时我问他，他说都款出来了还说自","box":[[187,456],[1051,457],[1051,481],[187,480]]},{"text":"已是左派，当时我说：朋大富同学你可能就是牛鬼蛇神，那天我是开玩笑，但是","box":[[193,508],[1049,508],[1049,527],[193,527]]},{"text":"说对了，我说工作组基本上是好的，但一下子没把局势铺开，工作组是有些缺点","box":[[190,554],[1046,555],[1046,576],[190,575]]},{"text":"有些人提意见是对工作组的帮助，可你（指前）这是反扑。","box":[[192,604],[820,604],[820,624],[192,624]]},{"text":"我看清华现在的大辩论会很好，现在的局面是好的局面，只准制大富写，不","box":[[239,652],[1052,651],[1052,674],[239,676]]},{"text":"准左派起来反击，那是不行的。左派可以起来斗争嘛。同志们不要把测大富估计","box":[[189,702],[1049,702],[1049,722],[189,722]]},{"text":"的过高，把他估计的过高是要上当的，他不过是一个到处奔走的小萃子而已，他","box":[[190,749],[1049,750],[1049,771],[190,770]]},{"text":"没本事。我们左派一定要把真正的黑线拟出来，不要把他看的了不起，他刚才跟","box":[[187,798],[1052,797],[1052,820],[187,822]]},{"text":"我说的（指看大字报时和前的辩论），就是无理取闹。","box":[[190,848],[771,848],[771,868],[190,868]]},{"text":"今天我不是以胖老头资格，而是以一个普通人的资格讲的。欢迎你们贴我的","box":[[242,897],[1049,897],[1049,917],[242,917]]},{"text":"大字报。大富不赞成，我就高兴。施大富不高兴，我就落实了。如果大家都不","box":[[190,945],[1049,945],[1049,965],[190,965]]},{"text":"赞成我，只有测大富同意，那我今天就出不了清华园了。","box":[[188,992],[796,993],[796,1016],[188,1015]]},{"text":"测大富说：信任朋大富的还有一二百人。","box":[[242,1044],[669,1044],[669,1064],[242,1064]]},{"text":"一同学插话：没有，吹牛。","box":[[239,1091],[522,1091],[522,1114],[239,1114]]},{"text":"薄：一二百没有，五六十总有吧！","box":[[239,1139],[597,1139],[597,1162],[239,1162]]},{"text":"一同学插话，没有。","box":[[237,1188],[447,1188],[447,1211],[237,1211]]},{"text":"薄：十个八个总有吧······（不清楚）请左派同学注意，我有点“保皇派”，","box":[[237,1235],[1047,1235],[1047,1261],[237,1261]]},{"text":"对跟腻大富走的人，包括聊大富自己，你们要是死命地跟他们走是要上当的。对","box":[[192,1289],[1048,1289],[1048,1306],[192,1306]]},{"text":"那些受蒙蔽的人要抓紧作工作，不要跟测大富走了。我们都是新中国的人，跟我","box":[[190,1335],[1051,1335],[1051,1355],[190,1355]]},{"text":"们来吧！要把他们拉过来，争取他们，如果他承认错误，那是欢迎的，这一条大","box":[[192,1385],[1051,1385],[1051,1405],[192,1405]]},{"text":"家是否赞成？这才叫真正的毛泽东思想。对这些人是交枪不杀，这些同志可能认","box":[[190,1434],[1049,1434],[1049,1454],[190,1454]]},{"text":"识错误，因而每一个左派同学...（不清）什么叫左派？","box":[[190,1481],[800,1481],[800,1504],[190,1504]]}],"dimensions":{"height":1755,"width":1241}}