{"ocr_results":[{"text":"126","box":[[128,108],[157,108],[157,129],[128,129]]},{"text":"我们究竞拒绝什么遗产？","box":[[324,108],[496,109],[496,128],[324,127]]},{"text":"农村无产阶级”的人们，斯卡尔金的答复在这一点上是极其值得","box":[[112,163],[711,163],[711,180],[112,180]]},{"text":"注意的。斯卡尔金说：“只要我们回想一下我国有多么广阔的土","box":[[109,196],[713,195],[713,216],[109,217]]},{"text":"地因为没有人耕种而荒废起来，这个反驳就不攻自破了。如果法","box":[[110,234],[712,234],[712,251],[110,251]]},{"text":"律不限制我们自由分配劳动力，那末在俄国只有那些职业乞写或","box":[[109,268],[713,266],[713,287],[109,289]]},{"text":"者是不可救药的堕落分子和酒鬼才会成为真正的无产者”（第144","box":[[109,304],[713,303],[713,323],[109,324]]},{"text":"页），一一一这是十八世纪经济学者和“启蒙者”的典型的观点，他们","box":[[109,340],[713,338],[713,358],[109,361]]},{"text":"相信：废除农奴制及其一切残余，将在大地上建立普遍幸福的国","box":[[110,375],[712,374],[712,394],[110,395]]},{"text":"度。一也许民粹派分子会蔑视斯卡尔金，说他不过是一个资产","box":[[109,410],[713,407],[713,428],[109,431]]},{"text":"者。不错，斯卡尔金当然是一个资产者，但他是进步资产阶级思想","box":[[109,446],[712,444],[712,464],[109,466]]},{"text":"体系的代表者，而民粹派分子的思想体系则是小资产阶级的，在许","box":[[109,482],[712,479],[712,499],[109,502]]},{"text":"多方面是反动的。至于农民的那些与整个社会发展的要求始终一","box":[[109,517],[713,515],[713,536],[109,538]]},{"text":"致的实际的和现实的利益，这个“资产者”却比民粹派分子还能捍","box":[[109,553],[712,550],[712,570],[109,573]]},{"text":"卫得好些！，","box":[[110,588],[245,588],[245,609],[110,609]]},{"text":"为了结束对斯卡尔金观点的说明，我们要补充几句：他反对等","box":[[153,624],[712,621],[712,641],[153,644]]},{"text":"级，主张一切等级只有一个法庭，“在理论上”同情不分等级的乡政","box":[[109,659],[713,656],[713,676],[109,680]]},{"text":"权，热烈拥护人民教育、特别是普遍教育，拥护自治和地方自治机","box":[[109,695],[712,693],[712,713],[109,715]]},{"text":"构，拥护广泛的农业信贷、特别是小额信贷，因为农民极其需要购","box":[[110,731],[712,728],[712,748],[110,751]]},{"text":"买土地。“曼彻斯特派”在这里又出面了：例如，斯卡尔金说，地方","box":[[110,767],[712,762],[712,783],[110,787]]},{"text":"自治局71的和城市的银行是“家长制的或原始的银行形式”，这些","box":[[112,802],[713,798],[713,818],[112,822]]},{"text":"银行应当让位于具有“一切优越性”的私人银行（第80页）。提高","box":[[110,838],[713,833],[713,854],[110,858]]},{"text":"土地价值，“只能在我们各省的工商业活动十分活跃的情况下才能","box":[[111,873],[713,869],[713,889],[111,893]]},{"text":"办到”（第71页）等等。","box":[[109,909],[314,909],[314,930],[109,930]]},{"text":"①反过来说：凡是我们在民粹派那里遇到的具有进步意义的实际措施，就其内容","box":[[139,959],[714,954],[714,974],[139,979]]},{"text":"说来，完全是资产阶级性质的措施，即正好对资本主义发展而不是对其他什么","box":[[174,984],[714,979],[714,996],[174,1002]]},{"text":"发展有利的指施。只有小资产者才提造理论，说扩大农民所有地，减少赋税，","box":[[174,1008],[712,1004],[712,1022],[174,1026]]},{"text":"实行移民，发放信贷，提高技术，整顿销售等等的措施，是为什么“人民生产”服","box":[[174,1033],[714,1029],[714,1046],[174,1050]]},{"text":"务的。","box":[[174,1058],[217,1058],[217,1076],[174,1076]]}],"dimensions":{"height":1199,"width":827}}